Workbook

Sheet Monetization factors
B2: Monetization factors :
B4: Table 2 : Overview of the impacts considered across the five assessed categories, associated indicators, valuation methods, monetization methods and factors, and their sources
B5: Category | C5: Impacts | D5: Indicators | E5: Valuation methods | F5: Monetization methods | G5: Original Monetization factors | H5: Original unit | I5: Value used in this study | J5: Unit | K5: Monetization factors source
B6: Environment | C6: Fine particulate matter formation | D6: kg PM2.5eq | E6: LCA | F6: Compensation | G6: 66.8 | H6: EUR 2022/kg PM2.5eq | I6: =G6*$D$44 -> 66.8 | J6: CHF/kg PM2.5eq | K6: True Price Foundation (2023)
B7: Environment | C7: Global warming | D7: kg CO2 eq | E7: LCA | F7: Restoration | G7: 0.163 | H7: EUR 2022/kg CO2 eq | I7: =G7*$D$44 -> 0.163 | J7: CHF/kg CO2 eq | K7: True Price Foundation (2023)
B8: Environment | C8: Fossil resource scarcity | D8: kg oil eq | E8: LCA | F8: Compensation | G8: 0.46 | H8: EUR 2022/kg oil eq | I8: =G8*$D$44 -> 0.46 | J8: CHF/kg oil eq | K8: True Price Foundation (2023)
B9: Environment | C9: Mineral resource scarcity | D9: kg Cu eq | E9: LCA | F9: Compensation | G9: 0.223 | H9: EUR 2022/kg Cu eq | I9: =G9*$D$44 -> 0.223 | J9: CHF/kg Cu eq | K9: True Price Foundation (2023)
B10: Environment | C10: Terrestrial ecotoxicity | D10: kg 1,4-DCB eq | E10: LCA | F10: Compensation | G10: =3 * 10^-4 -> 0.0003 | H10: EUR 2022/kg 1,4-DCB eq | I10: =G10*$D$44 -> 0.0003 | J10: CHF/kg 1,4-DCB eq | K10: True Price Foundation (2023)
B11: Environment | C11: Terrestrial acidification | D11: kg SO2 eq | E11: LCA | F11: Compensation | G11: 4.82 | H11: EUR 2022/kg SO2 eq | I11: =G11*$D$44 -> 4.82 | J11: CHF/kg SO2 eq | K11: True Price Foundation (2023)
B12: Environment | C12: Freshwater ecotoxicity | D12: kg 1,4-DCB eq | E12: LCA | F12: Compensation | G12: 0.0417 | H12: EUR 2022/kg 1,4-DCB eq | I12: =G12*$D$44 -> 0.0417 | J12: CHF/kg 1,4-DCB eq | K12: True Price Foundation (2023)
B13: Environment | C13: Freshwater eutrophication | D13: kg P eq | E13: LCA | F13: Compensation & restoration | G13: 209 | H13: EUR 2022/kg P eq | I13: =G13*$D$44 -> 209 | J13: CHF/kg P eq | K13: True Price Foundation (2023)
B14: Environment | C14: Marine ecotoxicity | D14: kg 1,4-DCB eq | E14: LCA | F14: Compensation | G14: =1.9 * 10^-3 -> 0.0019 | H14: EUR 2022/kg 1,4-DCB eq | I14: =G14*$D$44 -> 0.0019 | J14: CHF/kg 1,4-DCB eq | K14: True Price Foundation (2023)
B15: Environment | C15: Marine eutrophication | D15: kg N eq | E15: LCA | F15: Compensation & restoration | G15: 14.5 | H15: EUR 2022/kg N eq | I15: =G15*$D$44 -> 14.5 | J15: CHF/kg N eq | K15: True Price Foundation (2023)
B16: Livelihoods | C16: Gender wage gap | D16: CHF | E16: Own methodology | F16: Compensation | G16: 1.09 | H16: EUR 2022/EUR 2022 | I16: =G16*$D$44 -> 1.09 | J16: CHF/CHF | K16: True Price Foundation (2023)
B17: Livelihoods | C17: Statutory nominal gross wage gap | D17: CHF | E17: Own methodology | F17: Compensation | G17: 1.59 | H17: EUR 2022/EUR 2022 | I17: =G17*$D$44 -> 1.59 | J17: CHF/CHF | K17: True Price Foundation (2023)
B18: Livelihoods | C18: Children 5–11 in non-hazardous work | D18: %a | E18: Own methodology | F18: Restoration and retribution | G18: 9910 | H18: EUR 2022/FTEchild | I18: =G18*$D$44 -> 9910 | J18: CHF/FTEchild | K18: True Price Foundation (2023)
B19: Livelihoods | C19: Children 12–14 in non-hazardous work | D19: %a | E19: Own methodology | F19: Restoration and retribution | G19: 2380 | H19: EUR 2022/FTEchild | I19: =G19*$D$44 -> 2380 | J19: CHF/FTEchild | K19: True Price Foundation (2023)
B20: Livelihoods | C20: Children 5–14 in hazardous work | D20: %a | E20: Own methodology | F20: Restoration and retribution | G20: 25100 | H20: EUR 2022/FTEchild | I20: =G20*$D$44 -> 25100 | J20: CHF/FTEchild | K20: True Price Foundation (2023)
B21: Livelihoods | C21: Absence of social security | D21: %a | E21: Own methodology | F21: Retribution | G21: 2340 | H21: EUR 2022/FTE | I21: =G21*$D$44 -> 2340 | J21: CHF/FTE | K21: True Price Foundation (2023)
B22: Livelihoods | C22: Denied maternity leave | D22: CHF | E22: Own methodology | F22: Compensation | G22: 1.09 | H22: EUR 2022/EUR 2022 | I22: =G22*$D$44 -> 1.09 | J22: CHF/CHF | K22: True Price Foundation (2023)
B23: Livelihoods | C23: Workers without maternity leave | D23: %a | E23: Own methodology | F23: Retribution | G23: 1760 | H23: EUR 2022/FTE | I23: =G23*$D$44 -> 1760 | J23: CHF/FTE | K23: True Price Foundation (2023)
B24: Livelihoods | C24: Insured non-fatal incidents | D24: y^-1 | E24: Own methodology | F24: Compensation | G24: 3710 | H24: EUR 2022/incident | I24: =G24*$D$44 -> 3710 | J24: CHF/incident | K24: True Price Foundation (2023)
B25: Livelihoods | C25: Uninsured non-fatal incidents | D25: y^-1 | E25: Own methodology | F25: Compensation | G25: 3840 | H25: EUR 2022/incident | I25: =G25*$D$44 -> 3840 | J25: CHF/incident | K25: True Price Foundation (2023)
B26: Livelihoods | C26: Fatal incidents | D26: y^-1 | E26: Own methodology | F26: Compensation | G26: 3150000 | H26: EUR 2022/incident | I26: =G26*$D$44 -> 3150000 | J26: CHF/incident | K26: True Price Foundation (2023)
B27: Health | C27: Dietary impact of meat consumption | D27: DALYs | E27: Crosnier et al (2025) | F27: Restoration | G27: 80000 | H27: EUR 2022/DALY | I27: =G27*$D$44 -> 80000 | J27: CHF/DALY | K27: True Cost Initiative, TMG and Soil More Impacts (2014)
B28: Animal welfare | C28: Welfare impairments | D28: AQALY | E28: Espinosa et al (2025) | F28: Espinosa et al (2025) | G28: 100000 | H28: CHF/QALY | I28: 100000 | J28: CHF/QALY | K28: Pavic et al. (2014)
B29: {a} Proportion of agricultural work performed by people exposed to impact j
B30: Sources :
B31: True Cost Initiative and TMG and Soil More Impacts , 2022. True cost accounting agrifood handbook.
B32: URL: https://tca2f.org/wp-content/uploads/2022/03/TCA_Agrifood_Handbook.pdf
B33: True Price Foundation, 2023. Monetisation Factors for True Pricing. Technical Report. True Price Foundation.
B34: URL: https://www.trueprice.org/publications/monitisation-factors-for-true-pricing/
B35: Pavic, M., Pfeil, A.M., Szucs, T.D., 2014. Estimating the potential annual welfare impact of innovative drugs in use in switzerland. Frontiers in Public Health 2, 48.
B36: doi:10.3389/fpubh.2014.00048
B40: Exchange rates :
B42: Table 1 (Appendix A.2) : Annual exchange rates used to convert monetisation factors into Swiss Francs (CHF)
C43: Year | D43: Rate | E43: Source
B44: EUR per CHF | C44: 2022 | D44: 1 | E44: World Bank, Official exchange rate
B45: CHF per USD | C45: 2022 | D45: 0.95 | E45: World Bank, Official exchange rate
B47: Sources :
B48: World Bank. Official exchange rate (LCU per US$, period average). World Development Indicators.Data from the International Financial Statistics database, International Monetary Fund. 2022
B49: URL : https://data.worldbank.org/indicator/PA.NUS.FCRF

Sheet Production Systems Parameters
B2: Production systems parameters :
B4: Table 1 : Parameters characterizing production systems and used in the impact assessment.
B5: Production system | C5: Final live weight [kg] | D5: Pasture time [month] | E5: Feedlot time [month] | F5: Sources
B6: Swiss Intensive | C6: 520 | D6: 0 | E6: 16 | F6: Morel et al. (2021)
B7: Swiss Semi-intensive | C7: 520 | D7: 13 | E7: 5 | F7: Morel et al. (2021)
B8: Swiss Extensive | C8: 550 | D8: 23 | E8: 0 | F8: Morel et al. (2021)
B9: Uruguayan Semi-intensive | C9: 505 | D9: 19.5 | E9: 3.5 | F9: FAO and NZAGRC (2017)
B10: Uruguayan Extensive | C10: 505 | D10: 30.5 | E10: 0 | F10: FAO and NZAGRC (2017)
B11: Sources :
B12: Morel, I., Oberson, J.L., Schlegel, P., Chassot, A., Lehmann, E., Kessler, J., 2021. Apports alimentaires recommandés pour le bovin à l’engrais,
B13: in: Apports alimentaires recommandés pour les ruminants (Livre vert). Agroscope. chapter 10.
B14: https://www.agroscope.ch/livre-vert
B15: FAO, NZAGRC, 2017. Low emissions development of the beef cattle sector in uruguay.
B16: https://www.ccacoalition.org/resources/low-emissions-development-beef-cattle-sector-uruguay
B21: Yield (live weight - edible meat) | C21: =41 -> 41 | D21: [%]
B22: Source:
B23: Verheyen, L.A.H.M., Wiersema, D., Hulshoff-Pol, L.W., Brandjes, P., Westra, P.J., Bos, J.F.F.P., Jansen, J.C.M., 1996.
B24: Management of Waste from Animal Product Processing. Food and Agriculture Organization of the United Nations (FAO).
B25: chapter II: Slaughterhouses. section 2.1.2: Quantities of by-products.
B26: https://openknowledge.fao.org/items/05ea9fcc-c0ff-459c-b40e-0883e59c9b1a

Sheet Results
B2: Results :
B4: Results : Hidden costs per indicator
D5: Hidden cost [CHF/kg]
B6: Category | C6: Impacts | D6: Intensive - Switzerland | E6: Semi-Intensive - Switzerland | F6: Extensive - Switzerland | G6: Semi-Itensive - Uruguay | H6: Extensive - Uruguay
B7: Environment | C7: Fine particulate matter formation | D7: =Environment!L8 -> 1.3509986 | E7: =Environment!M8 -> 2.0715354 | F7: =Environment!N8 -> 3.0981901 | G7: =Environment!O8 -> 4.0480117 | H7: =Environment!P8 -> 5.0893946
B8: Environment | C8: Fossil resource scarcity | D8: =Environment!L9 -> 0.29514279 | E8: =Environment!M9 -> 0.29873349 | F8: =Environment!N9 -> 0.41622056 | G8: =Environment!O9 -> 0.55069935 | H8: =Environment!P9 -> 0.65209134
B9: Environment | C9: Freshwater ecotoxicity | D9: =Environment!L10 -> 0.0064735027 | E9: =Environment!M10 -> 0.0046307289 | F9: =Environment!N10 -> 0.0051564892 | G9: =Environment!O10 -> 0.0098960712 | H9: =Environment!P10 -> 0.01068174
B10: Environment | C10: Freshwater eutrophication | D10: =Environment!L11 -> 0.38406012 | E10: =Environment!M11 -> 0.30386947 | F10: =Environment!N11 -> 0.32032666 | G10: =Environment!O11 -> 0.74680213 | H10: =Environment!P11 -> 0.75152396
B11: Environment | C11: Global warming | D11: =Environment!L12 -> 2.4856122 | E11: =Environment!M12 -> 5.3703111 | F11: =Environment!N12 -> 7.4657598 | G11: =Environment!O12 -> 10.31961 | H11: =Environment!P12 -> 11.815481
B12: Environment | C12: Marine ecotoxicity | D12: =Environment!L13 -> 0.00028251464 | E12: =Environment!M13 -> 0.00027407686 | F12: =Environment!N13 -> 0.00032617325 | G12: =Environment!O13 -> 0.00061202632 | H12: =Environment!P13 -> 0.00066718036
B13: Environment | C13: Marine eutrophication | D13: =Environment!L14 -> 0.19899726 | E13: =Environment!M14 -> 0.1687117 | F13: =Environment!N14 -> 0.17517824 | G13: =Environment!O14 -> 0.42925537 | H13: =Environment!P14 -> 0.4150143
B14: Environment | C14: Mineral resource scarcity | D14: =Environment!L15 -> 0.014158093 | E14: =Environment!M15 -> 0.023382446 | F14: =Environment!N15 -> 0.021667627 | G14: =Environment!O15 -> 0.032055483 | H14: =Environment!P15 -> 0.030392257
B15: Environment | C15: Terrestrial acidification | D15: =Environment!L16 -> 0.62629698 | E15: =Environment!M16 -> 1.0632407 | F15: =Environment!N16 -> 1.6104389 | G15: =Environment!O16 -> 2.0231848 | H15: =Environment!P16 -> 2.6021083
B16: Environment | C16: Terrestrial ecotoxicity | D16: =Environment!L17 -> 0.0031865633 | E16: =Environment!M17 -> 0.0023137448 | F16: =Environment!N17 -> 0.0027477039 | G16: =Environment!O17 -> 0.0047874229 | H16: =Environment!P17 -> 0.005194409
B17: Livelihoods | C17: Gender wage gap | D17: =Livelihoods!AF8 -> 0.59933486 | E17: =Livelihoods!AG8 -> 0.55040957 | F17: =Livelihoods!AH8 -> 0.60809766 | G17: =Livelihoods!AI8 -> 0.037516586 | H17: =Livelihoods!AJ8 -> 0.060929664
B18: Livelihoods | C18: Statutory nominal gross wage gap | D18: =Livelihoods!AF9 -> 0.10541531 | E18: =Livelihoods!AG9 -> 0.096809982 | F18: =Livelihoods!AH9 -> 0.10695658 | G18: =Livelihoods!AI9 -> 0 | H18: =Livelihoods!AJ9 -> 0
B19: Livelihoods | C19: Children 5–11 in non-hazardous work | D19: =Livelihoods!AF10 -> 0 | E19: =Livelihoods!AG10 -> 0 | F19: =Livelihoods!AH10 -> 0 | G19: =Livelihoods!AI10 -> 0.0028116039 | H19: =Livelihoods!AJ10 -> 0.0045662492
B20: Livelihoods | C20: Children 12–14 in non-hazardous work | D20: =Livelihoods!AF11 -> 0 | E20: =Livelihoods!AG11 -> 0 | F20: =Livelihoods!AH11 -> 0 | G20: =Livelihoods!AI11 -> 0.0023372774 | H20: =Livelihoods!AJ11 -> 0.0037959085
B21: Livelihoods | C21: Children 5–14 in hazardous work | D21: =Livelihoods!AF12 -> 0 | E21: =Livelihoods!AG12 -> 0 | F21: =Livelihoods!AH12 -> 0 | G21: =Livelihoods!AI12 -> 0.0016651192 | H21: =Livelihoods!AJ12 -> 0.0027042747
B22: Livelihoods | C22: Absence of social security | D22: =Livelihoods!AF13 -> 0.0065359995 | E22: =Livelihoods!AG13 -> 0.0060024485 | F22: =Livelihoods!AH13 -> 0.0066315614 | G22: =Livelihoods!AI13 -> 0.013780746 | H22: =Livelihoods!AJ13 -> 0.022380934
B23: Livelihoods | C23: Denied maternity leave | D23: =Livelihoods!AF14 -> 1.3647528e-05 | E23: =Livelihoods!AG14 -> 1.2533444e-05 | F23: =Livelihoods!AH14 -> 1.3847066e-05 | G23: =Livelihoods!AI14 -> 2.6135522e-05 | H23: =Livelihoods!AJ14 -> 4.2445988e-05
B24: Livelihoods | C24: Workers without maternity leave | D24: =Livelihoods!AF15 -> 0.0001162673 | E24: =Livelihoods!AG15 -> 0.00010677609 | F24: =Livelihoods!AH15 -> 0.00011796723 | G24: =Livelihoods!AI15 -> 3.6231037e-05 | H24: =Livelihoods!AJ15 -> 5.8841838e-05
B25: Livelihoods | C25: Insured non-fatal incidents | D25: =Livelihoods!AF16 -> 0.0024868883 | E25: =Livelihoods!AG16 -> 0.002283877 | F25: =Livelihoods!AH16 -> 0.0025232487 | G25: =Livelihoods!AI16 -> 0.0002557744 | H25: =Livelihoods!AJ16 -> 0.00041539623
B26: Livelihoods | C26: Uninsured non-fatal incidents | D26: =Livelihoods!AF17 -> 0.00020870513 | E26: =Livelihoods!AG17 -> 0.00019166798 | F26: =Livelihoods!AH17 -> 0.00021175658 | G26: =Livelihoods!AI17 -> 0.00011345865 | H26: =Livelihoods!AJ17 -> 0.0001842651
B27: Livelihoods | C27: Fatal incidents | D27: =Livelihoods!AF18 -> 0.00398611 | E27: =Livelihoods!AG18 -> 0.0036607133 | F27: =Livelihoods!AH18 -> 0.0040443904 | G27: =Livelihoods!AI18 -> 0.0018153192 | H27: =Livelihoods!AJ18 -> 0.0029482104
B28: Health | C28: Dietary impact of meat consumption | D28: =Health!$V$14 -> 2.0992405 | E28: =Health!$V$14 -> 2.0992405 | F28: =Health!$V$14 -> 2.0992405 | G28: =Health!$V$14 -> 2.0992405 | H28: =Health!$V$14 -> 2.0992405
B29: Animal welfare | C29: Welfare impairements in Nutrition | D29: ='Animal welfare'!Z14 -> 0.89660963 | E29: ='Animal welfare'!AA14 -> 0.74817142 | F29: ='Animal welfare'!AB14 -> 0.91507714 | G29: ='Animal welfare'!AC14 -> 0.37317292 | H29: ='Animal welfare'!AD14 -> 0
B30: Animal welfare | C30: Welfare impairements in Environment | D30: ='Animal welfare'!Z15 -> 4.6443284 | E30: ='Animal welfare'!AA15 -> 0.18098383 | F30: ='Animal welfare'!AB15 -> 1.4525176 | G30: ='Animal welfare'!AC15 -> 0.13320659 | H30: ='Animal welfare'!AD15 -> 0
B31: Animal welfare | C31: Welfare impairements in Health | D31: ='Animal welfare'!Z16 -> 3.5219768 | E31: ='Animal welfare'!AA16 -> 0.45450548 | F31: ='Animal welfare'!AB16 -> 0.57493627 | G31: ='Animal welfare'!AC16 -> 0.43196532 | H31: ='Animal welfare'!AD16 -> 0
B32: Animal welfare | C32: Welfare impairements in Behaviour | D32: ='Animal welfare'!Z17 -> 13.330734 | E32: ='Animal welfare'!AA17 -> 3.014089 | F32: ='Animal welfare'!AB17 -> 1.0248864 | G32: ='Animal welfare'!AC17 -> 2.3585669 | H32: ='Animal welfare'!AD17 -> 0
B33: Animal welfare | C33: Premature Mortality | D33: ='Animal welfare'!Z18 -> 18.25576 | E33: ='Animal welfare'!AA18 -> 13.879414 | F33: ='Animal welfare'!AB18 -> 0.9927471 | G33: ='Animal welfare'!AC18 -> 8.9767631 | H33: ='Animal welfare'!AD18 -> 0
B35: Results : Hidden costs per impact category
C36: Hidden cost [CHF/kg]
B37: Category | C37: Intensive - Switzerland | D37: Semi-Intensive - Switzerland | E37: Extensive - Switzerland | F37: Semi-Itensive - Uruguay | G37: Extensive - Uruguay
B38: Environment | C38: =SUM(D7:D16) -> 5.3652086 | D38: =SUM(E7:E16) -> 9.3070029 | E38: =SUM(F7:F16) -> 13.116012 | F38: =SUM(G7:G16) -> 18.164914 | G38: =SUM(H7:H16) -> 21.372549
B39: Livelihoods | C39: =SUM(D17:D27) -> 0.71809779 | D39: =SUM(E17:E27) -> 0.65947757 | E39: =SUM(F17:F27) -> 0.728597 | F39: =SUM(G17:G27) -> 0.060358252 | G39: =SUM(H17:H27) -> 0.09802619
B40: Health | C40: =SUM(D28) -> 2.0992405 | D40: =SUM(E28) -> 2.0992405 | E40: =SUM(F28) -> 2.0992405 | F40: =SUM(G28) -> 2.0992405 | G40: =SUM(H28) -> 2.0992405
B41: Animal welfare | C41: =SUM(D29:D33) -> 40.649409 | D41: =SUM(E29:E33) -> 18.277164 | E41: =SUM(F29:F33) -> 4.9601645 | F41: =SUM(G29:G33) -> 12.273675 | G41: =SUM(H29:H33) -> 0
B42: TOT | C42: =SUM(C38:C41) -> 48.831956 | D42: =SUM(D38:D41) -> 30.342884 | E42: =SUM(E38:E41) -> 20.904014 | F42: =SUM(F38:F41) -> 32.598188 | G42: =SUM(G38:G41) -> 23.569816
B45: Results : Environmental Hidden costs (aggragated)
C46: Hidden cost [CHF/kg]
C47: Intensive - Switzerland | D47: Semi-Intensive - Switzerland | E47: Extensive - Switzerland | F47: Semi-Itensive - Uruguay | G47: Extensive - Uruguay
B48: Others | C48: =D16+D14+D12+D9 -> 0.024100674 | D48: =E16+E14+E12+E9 -> 0.030600996 | E48: =F16+F14+F12+F9 -> 0.029897993 | F48: =G16+G14+G12+G9 -> 0.047351004 | G48: =H16+H14+H12+H9 -> 0.046935587
B49: Marine eutrophication | C49: =D13 -> 0.19899726 | D49: =E13 -> 0.1687117 | E49: =F13 -> 0.17517824 | F49: =G13 -> 0.42925537 | G49: =H13 -> 0.4150143
B50: Terrestrial acidification | C50: =D15 -> 0.62629698 | D50: =E15 -> 1.0632407 | E50: =F15 -> 1.6104389 | F50: =G15 -> 2.0231848 | G50: =H15 -> 2.6021083
B51: Freshwater eutrophication | C51: =D10 -> 0.38406012 | D51: =E10 -> 0.30386947 | E51: =F10 -> 0.32032666 | F51: =G10 -> 0.74680213 | G51: =H10 -> 0.75152396
B52: Fossil resource scarcity | C52: =D8 -> 0.29514279 | D52: =E8 -> 0.29873349 | E52: =F8 -> 0.41622056 | F52: =G8 -> 0.55069935 | G52: =H8 -> 0.65209134
B53: Global warming | C53: =D11 -> 2.4856122 | D53: =E11 -> 5.3703111 | E53: =F11 -> 7.4657598 | F53: =G11 -> 10.31961 | G53: =H11 -> 11.815481
B54: Fine particulate matter formation | C54: =D7 -> 1.3509986 | D54: =E7 -> 2.0715354 | E54: =F7 -> 3.0981901 | F54: =G7 -> 4.0480117 | G54: =H7 -> 5.0893946
B56: Results : Livelihoods Hidden costs (aggragated)
C57: Hidden cost [CHF/kg]
C58: Intensive - Switzerland | D58: Semi-Intensive - Switzerland | E58: Extensive - Switzerland | F58: Semi-Itensive - Uruguay | G58: Extensive - Uruguay
B59: Child labour | C59: =SUM(D19:D21) -> 0 | D59: =SUM(E19:E21) -> 0 | E59: =SUM(F19:F21) -> 0 | F59: =SUM(G19:G21) -> 0.0068140006 | G59: =SUM(H19:H21) -> 0.011066432
B60: Workers rights | C60: =SUM(D22:D24) -> 0.0066659143 | D60: =SUM(E22:E24) -> 0.006121758 | E60: =SUM(F22:F24) -> 0.0067633757 | F60: =SUM(G22:G24) -> 0.013843113 | G60: =SUM(H22:H24) -> 0.022482222
B61: Gender wage gap | C61: =D17 -> 0.59933486 | D61: =E17 -> 0.55040957 | E61: =F17 -> 0.60809766 | F61: =G17 -> 0.037516586 | G61: =H17 -> 0.060929664
B62: Wage gap (minimum wage) | C62: =D18 -> 0.10541531 | D62: =E18 -> 0.096809982 | E62: =F18 -> 0.10695658 | F62: =G18 -> 0 | G62: =H18 -> 0
B63: Occupational safety | C63: =SUM(D25:D27) -> 0.0066817034 | D63: =SUM(E25:E27) -> 0.0061362583 | E63: =SUM(F25:F27) -> 0.0067793957 | F63: =SUM(G25:G27) -> 0.0021845523 | G63: =SUM(H25:H27) -> 0.0035478718

Sheet Figures
B2: Overall results :
B23: Environment :
B47: Livelihoods
B71: Health :
B93: Animal Welfare :

Sheet Environment
B2: Environment :
B4: Impact assessment | K4: Impact monetization
B7: Impact category | C7: Reference unit | D7: Intensive - Switzerland | E7: Semi-Intensive - Switzerland | F7: Extensive - Switzerland | G7: Semi - Intensive - Uruguay | H7: Extensive - Uruguay | K7: Impact category | L7: Intensive - Switzerland | M7: Semi-Intensive - Switzerland | N7: Extensive - Switzerland | O7: Semi - Intensive - Uruguay | P7: Extensive - Uruguay | Q7: Hidden costs
B8: Fine particulate matter formation | C8: kg PM2.5 eq | D8: 0.02022453 | E8: 0.031011009 | F8: 0.046380092 | G8: 0.060598977 | H8: 0.076188542 | K8: Fine particulate matter formation | L8: =VLOOKUP(B8,'Monetization factors'!$C$6:$I$28, 7,FALSE)*D8 -> 1.3509986 | M8: =VLOOKUP(B8,'Monetization factors'!$C$6:$I$28, 7,FALSE)*E8 -> 2.0715354 | N8: =VLOOKUP(B8,'Monetization factors'!$C$6:$I$28, 7,FALSE)*F8 -> 3.0981901 | O8: =VLOOKUP(B8,'Monetization factors'!$C$6:$I$28, 7,FALSE)*G8 -> 4.0480117 | P8: =VLOOKUP(B8,'Monetization factors'!$C$6:$I$28, 7,FALSE)*H8 -> 5.0893946 | Q8: [CHF/kg]
B9: Fossil resource scarcity | C9: kg oil eq | D9: 0.64161475 | E9: 0.64942064 | F9: 0.9048273 | G9: 1.1971725 | H9: 1.4175899 | K9: Fossil resource scarcity | L9: =VLOOKUP(B9,'Monetization factors'!$C$6:$I$28, 7,FALSE)*D9 -> 0.29514279 | M9: =VLOOKUP(B9,'Monetization factors'!$C$6:$I$28, 7,FALSE)*E9 -> 0.29873349 | N9: =VLOOKUP(B9,'Monetization factors'!$C$6:$I$28, 7,FALSE)*F9 -> 0.41622056 | O9: =VLOOKUP(B9,'Monetization factors'!$C$6:$I$28, 7,FALSE)*G9 -> 0.55069935 | P9: =VLOOKUP(B9,'Monetization factors'!$C$6:$I$28, 7,FALSE)*H9 -> 0.65209134 | Q9: [CHF/kg]
B10: Freshwater ecotoxicity | C10: kg 1,4-DCB | D10: 0.15523987 | E10: 0.11104866 | F10: 0.12365682 | G10: 0.23731586 | H10: 0.25615683 | K10: Freshwater ecotoxicity | L10: =VLOOKUP(B10,'Monetization factors'!$C$6:$I$28, 7,FALSE)*D10 -> 0.0064735027 | M10: =VLOOKUP(B10,'Monetization factors'!$C$6:$I$28, 7,FALSE)*E10 -> 0.0046307289 | N10: =VLOOKUP(B10,'Monetization factors'!$C$6:$I$28, 7,FALSE)*F10 -> 0.0051564892 | O10: =VLOOKUP(B10,'Monetization factors'!$C$6:$I$28, 7,FALSE)*G10 -> 0.0098960712 | P10: =VLOOKUP(B10,'Monetization factors'!$C$6:$I$28, 7,FALSE)*H10 -> 0.01068174 | Q10: [CHF/kg]
B11: Freshwater eutrophication | C11: kg P eq | D11: 0.0018376082 | E11: 0.0014539209 | F11: 0.0015326635 | G11: 0.0035732159 | H11: 0.0035958084 | K11: Freshwater eutrophication | L11: =VLOOKUP(B11,'Monetization factors'!$C$6:$I$28, 7,FALSE)*D11 -> 0.38406012 | M11: =VLOOKUP(B11,'Monetization factors'!$C$6:$I$28, 7,FALSE)*E11 -> 0.30386947 | N11: =VLOOKUP(B11,'Monetization factors'!$C$6:$I$28, 7,FALSE)*F11 -> 0.32032666 | O11: =VLOOKUP(B11,'Monetization factors'!$C$6:$I$28, 7,FALSE)*G11 -> 0.74680213 | P11: =VLOOKUP(B11,'Monetization factors'!$C$6:$I$28, 7,FALSE)*H11 -> 0.75152396 | Q11: [CHF/kg]
B12: Global warming | C12: kg CO2 eq | D12: 15.249155 | E12: 32.946694 | F12: 45.802207 | G12: 63.31049 | H12: 72.487614 | K12: Global warming | L12: =VLOOKUP(B12,'Monetization factors'!$C$6:$I$28, 7,FALSE)*D12 -> 2.4856122 | M12: =VLOOKUP(B12,'Monetization factors'!$C$6:$I$28, 7,FALSE)*E12 -> 5.3703111 | N12: =VLOOKUP(B12,'Monetization factors'!$C$6:$I$28, 7,FALSE)*F12 -> 7.4657598 | O12: =VLOOKUP(B12,'Monetization factors'!$C$6:$I$28, 7,FALSE)*G12 -> 10.31961 | P12: =VLOOKUP(B12,'Monetization factors'!$C$6:$I$28, 7,FALSE)*H12 -> 11.815481 | Q12: [CHF/kg]
B13: Marine ecotoxicity | C13: kg 1,4-DCB | D13: 0.14869192 | E13: 0.14425098 | F13: 0.17167013 | G13: 0.32211912 | H13: 0.35114756 | K13: Marine ecotoxicity | L13: =VLOOKUP(B13,'Monetization factors'!$C$6:$I$28, 7,FALSE)*D13 -> 0.00028251464 | M13: =VLOOKUP(B13,'Monetization factors'!$C$6:$I$28, 7,FALSE)*E13 -> 0.00027407686 | N13: =VLOOKUP(B13,'Monetization factors'!$C$6:$I$28, 7,FALSE)*F13 -> 0.00032617325 | O13: =VLOOKUP(B13,'Monetization factors'!$C$6:$I$28, 7,FALSE)*G13 -> 0.00061202632 | P13: =VLOOKUP(B13,'Monetization factors'!$C$6:$I$28, 7,FALSE)*H13 -> 0.00066718036 | Q13: [CHF/kg]
B14: Marine eutrophication | C14: kg N eq | D14: 0.013723949 | E14: 0.01163529 | F14: 0.012081258 | G14: 0.029603818 | H14: 0.028621676 | K14: Marine eutrophication | L14: =VLOOKUP(B14,'Monetization factors'!$C$6:$I$28, 7,FALSE)*D14 -> 0.19899726 | M14: =VLOOKUP(B14,'Monetization factors'!$C$6:$I$28, 7,FALSE)*E14 -> 0.1687117 | N14: =VLOOKUP(B14,'Monetization factors'!$C$6:$I$28, 7,FALSE)*F14 -> 0.17517824 | O14: =VLOOKUP(B14,'Monetization factors'!$C$6:$I$28, 7,FALSE)*G14 -> 0.42925537 | P14: =VLOOKUP(B14,'Monetization factors'!$C$6:$I$28, 7,FALSE)*H14 -> 0.4150143 | Q14: [CHF/kg]
B15: Mineral resource scarcity | C15: kg Cu eq | D15: 0.063489206 | E15: 0.10485402 | F15: 0.097164247 | G15: 0.14374656 | H15: 0.13628815 | K15: Mineral resource scarcity | L15: =VLOOKUP(B15,'Monetization factors'!$C$6:$I$28, 7,FALSE)*D15 -> 0.014158093 | M15: =VLOOKUP(B15,'Monetization factors'!$C$6:$I$28, 7,FALSE)*E15 -> 0.023382446 | N15: =VLOOKUP(B15,'Monetization factors'!$C$6:$I$28, 7,FALSE)*F15 -> 0.021667627 | O15: =VLOOKUP(B15,'Monetization factors'!$C$6:$I$28, 7,FALSE)*G15 -> 0.032055483 | P15: =VLOOKUP(B15,'Monetization factors'!$C$6:$I$28, 7,FALSE)*H15 -> 0.030392257 | Q15: [CHF/kg]
B16: Terrestrial acidification | C16: kg SO2 eq | D16: 0.12993713 | E16: 0.22058936 | F16: 0.33411595 | G16: 0.41974788 | H16: 0.53985648 | K16: Terrestrial acidification | L16: =VLOOKUP(B16,'Monetization factors'!$C$6:$I$28, 7,FALSE)*D16 -> 0.62629698 | M16: =VLOOKUP(B16,'Monetization factors'!$C$6:$I$28, 7,FALSE)*E16 -> 1.0632407 | N16: =VLOOKUP(B16,'Monetization factors'!$C$6:$I$28, 7,FALSE)*F16 -> 1.6104389 | O16: =VLOOKUP(B16,'Monetization factors'!$C$6:$I$28, 7,FALSE)*G16 -> 2.0231848 | P16: =VLOOKUP(B16,'Monetization factors'!$C$6:$I$28, 7,FALSE)*H16 -> 2.6021083 | Q16: [CHF/kg]
B17: Terrestrial ecotoxicity | C17: kg 1,4-DCB | D17: 10.621878 | E17: 7.7124826 | F17: 9.159013 | G17: 15.958076 | H17: 17.314697 | K17: Terrestrial ecotoxicity | L17: =VLOOKUP(B17,'Monetization factors'!$C$6:$I$28, 7,FALSE)*D17 -> 0.0031865633 | M17: =VLOOKUP(B17,'Monetization factors'!$C$6:$I$28, 7,FALSE)*E17 -> 0.0023137448 | N17: =VLOOKUP(B17,'Monetization factors'!$C$6:$I$28, 7,FALSE)*F17 -> 0.0027477039 | O17: =VLOOKUP(B17,'Monetization factors'!$C$6:$I$28, 7,FALSE)*G17 -> 0.0047874229 | P17: =VLOOKUP(B17,'Monetization factors'!$C$6:$I$28, 7,FALSE)*H17 -> 0.005194409 | Q17: [CHF/kg]
K18: Total | L18: =SUM(L8:L17) -> 5.3652086 | M18: =SUM(M8:M17) -> 9.3070029 | N18: =SUM(N8:N17) -> 13.116012 | O18: =SUM(O8:O17) -> 18.164914 | P18: =SUM(P8:P17) -> 21.372549 | Q18: [CHF/kg]
B19: LCA results :
B20: DataBase : | C20: Agribalyse (3.01)
B21: Impact method: | C21: ReCiPe 2016 Midpoint (H)
B22: Normalisation & weighting set: | C22: World (2010) H
B23: Allocation method: | C23: process defaults
B24: Functional Unit : | C24: 1 kg of bovine meat

Sheet Livelihoods
B2: Livelihoods
B4: Input data | L4: Impact assessment | V4: Impact allocation | AE4: Impact monetization
L5: (Appendix C.2) | V5: (Appendix C.5)
B7: Impact assessement input data | L7: Intermediary results for child labour impact assessment in Uruguay | AE7: Impact | AF7: Intensive - Switzerland | AG7: Semi-Intensive - Switzerland | AH7: Extensive - Switzerland | AI7: Semi - Intensive - Uruguay | AJ7: Extensive - Uruguay | AK7: Hidden costs
L8: Parameter | M8: Age group | N8: Value | O8: Unit | V8: Agricultural FTE derivation : | AE8: Gender wage gap | AF8: =$N$22*W32*VLOOKUP(AE8,'Monetization factors'!$C$6:$I$28, 7,FALSE) -> 0.59933486 | AG8: =$N$22*X32*VLOOKUP(AE8,'Monetization factors'!$C$6:$I$28, 7,FALSE) -> 0.55040957 | AH8: =$N$22*Y32*VLOOKUP(AE8,'Monetization factors'!$C$6:$I$28, 7,FALSE) -> 0.60809766 | AI8: =$O$22*Z32*VLOOKUP(AE8,'Monetization factors'!$C$6:$I$28, 7,FALSE) -> 0.037516586 | AJ8: =$O$22*AA32*VLOOKUP(AE8,'Monetization factors'!$C$6:$I$28, 7,FALSE) -> 0.060929664 | AK8: [CHF/kg]
B9: Table 6 (Appendix C.1) : Input data used for the assessment of child labour impacts in Uruguay. | L9: Number of working children | M9: 5–11 | N9: =D11+D12/(14-9+1)*(11-9+1) -> 14200 | O9: indiv. | V9: (Appendix C.3) | AE9: Wage gap with minimum wage | AF9: =$N$23*W32*VLOOKUP("Statutory nominal gross wage gap",'Monetization factors'!$C$6:$I$28, 7,FALSE) -> 0.10541531 | AG9: =$N$23*X32*VLOOKUP("Statutory nominal gross wage gap",'Monetization factors'!$C$6:$I$28, 7,FALSE) -> 0.096809982 | AH9: =$N$23*Y32*VLOOKUP("Statutory nominal gross wage gap",'Monetization factors'!$C$6:$I$28, 7,FALSE) -> 0.10695658 | AI9: =$O$23*Z32*VLOOKUP("Statutory nominal gross wage gap",'Monetization factors'!$C$6:$I$28, 7,FALSE) -> 0 | AJ9: =$O$23*AA32*VLOOKUP("Statutory nominal gross wage gap",'Monetization factors'!$C$6:$I$28, 7,FALSE) -> 0 | AK9: [CHF/kg]
B10: Parameter | C10: Age group | D10: Value | E10: Unit | F10: Year | G10: Database / Source | H10: Indicator | I10: Sector | M10: 12–14 | N10: =D12/(14-9+1)*(14-12+1) -> 10900 | O10: indiv. | V10: Table 8 (Appendix C.3) : Labour intensity in the agricultural sector in Switzerland and Uruguay. | AE10: Children 5–14 in hazardous work | AF10: =N24/100*W33*VLOOKUP(AE10,'Monetization factors'!$C$6:$I$28, 7,FALSE) -> 0 | AG10: =N24/100*X33*VLOOKUP($AE10,'Monetization factors'!$C$6:$I$28, 7,FALSE) -> 0 | AH10: =N24/100*Y33*VLOOKUP($AE10,'Monetization factors'!$C$6:$I$28, 7,FALSE) -> 0 | AI10: =$O$24/100*Z33*VLOOKUP($AE10,'Monetization factors'!$C$6:$I$28, 7,FALSE) -> 0.0028116039 | AJ10: =$O$24/100*AA33*VLOOKUP($AE10,'Monetization factors'!$C$6:$I$28, 7,FALSE) -> 0.0045662492 | AK10: [CHF/kg]
B11: Number of working children aged a₁–a₂ years | C11: 5–8 | D11: 3300 | E11: indiv. | F11: 2024 | G11: ENSANNA | H11: Child labour by age group | I11: National | L11: Number of children in hazardeous work | M11: 5–11 | N11: =D13+D18/(14-9+1)*(11-9+1) -> 2725 | O11: indiv. | V11: Country | W11: FTE | X11: W_leave | AE11: Children 5–11 in non-hazardous work | AF11: =$N$25/100*W$33*VLOOKUP(AE11,'Monetization factors'!$C$6:$I$28, 7,FALSE) -> 0 | AG11: =$N$25/100*X$33*VLOOKUP($AE$11,'Monetization factors'!$C$6:$I$28, 7,FALSE) -> 0 | AH11: =$N$25/100*Y$33*VLOOKUP($AE$11,'Monetization factors'!$C$6:$I$28, 7,FALSE) -> 0 | AI11: =$O$25/100*Z$33*VLOOKUP($AE$11,'Monetization factors'!$C$6:$I$28, 7,FALSE) -> 0.0023372774 | AJ11: =$O$25/100*AA$33*VLOOKUP($AE$11,'Monetization factors'!$C$6:$I$28, 7,FALSE) -> 0.0037959085 | AK11: [CHF/kg]
C12: 9–14 | D12: 21800 | E12: indiv. | F12: 2024 | M12: 12–14 | N12: =D18/(14-9+1)*(14-12+1) -> 2725 | O12: indiv. | W12: [h/yr] | X12: [week/yr] | AE12: Children 12–14 in non-hazardous work | AF12: =$N$26/100*W$33*VLOOKUP(AE12,'Monetization factors'!$C$6:$I$28, 7,FALSE) -> 0 | AG12: =$N$26/100*X$33*VLOOKUP($AE$12,'Monetization factors'!$C$6:$I$28, 7,FALSE) -> 0 | AH12: =$N$26/100*Y$33*VLOOKUP($AE$12,'Monetization factors'!$C$6:$I$28, 7,FALSE) -> 0 | AI12: =$O$26/100*Z$33*VLOOKUP($AE$11,'Monetization factors'!$C$6:$I$28, 7,FALSE) -> 0.0016651192 | AJ12: =$O$26/100*AA$33*VLOOKUP($AE$11,'Monetization factors'!$C$6:$I$28, 7,FALSE) -> 0.0027042747 | AK12: [CHF/kg]
B13: Number of children aged a₁–a₂ years in hazardous work | C13: 5–8 | D13: 0 | E13: indiv. | F13: 2024 | G13: ENSANNA | H13: Children engaged in child labour, by category and age | I13: National | V13: Switzerland | W13: =(C129*C118/SUM(C114:C118)+C130*C117/SUM(C114:C118)+C131*C116/SUM(C114:C118)+C132*C115/SUM(C114:C118)+C133*C114/SUM(C114:C118))*(52-AVERAGE(D129:D133)) -> 2550.7883 | X13: =AVERAGE(D129:D133) -> 4 | AE13: Absence of social security | AF13: =$N$27/100*W$33*VLOOKUP($AE$13,'Monetization factors'!$C$6:$I$28, 7,FALSE) -> 0.0065359995 | AG13: =$N$27/100*X$33*VLOOKUP($AE$13,'Monetization factors'!$C$6:$I$28, 7,FALSE) -> 0.0060024485 | AH13: =$N$27/100*Y$33*VLOOKUP($AE$13,'Monetization factors'!$C$6:$I$28, 7,FALSE) -> 0.0066315614 | AI13: =$O$27/100*Z$33*VLOOKUP($AE$13,'Monetization factors'!$C$6:$I$28, 7,FALSE) -> 0.013780746 | AJ13: =$O$27/100*AA$33*VLOOKUP($AE$13,'Monetization factors'!$C$6:$I$28, 7,FALSE) -> 0.022380934 | AK13: [CHF/kg]
L14: Intermediary results for impact assessment | V14: Uruguay | W14: =C144*(52-C146/7) -> 2358.8571 | X14: =C146/7 -> 2.8571429 | AE14: Workers without maternity leave | AF14: =$N$28/100*W$33*VLOOKUP($AE$14,'Monetization factors'!$C$6:$I$28, 7,FALSE) -> 1.3647528e-05 | AG14: =$N$28/100*X$33*VLOOKUP($AE$14,'Monetization factors'!$C$6:$I$28, 7,FALSE) -> 1.2533444e-05 | AH14: =$N$28/100*Y$33*VLOOKUP($AE$14,'Monetization factors'!$C$6:$I$28, 7,FALSE) -> 1.3847066e-05 | AI14: =$O$28/100*Z$33*VLOOKUP($AE$14,'Monetization factors'!$C$6:$I$28, 7,FALSE) -> 2.6135522e-05 | AJ14: =$O$28/100*AA$33*VLOOKUP($AE$14,'Monetization factors'!$C$6:$I$28, 7,FALSE) -> 4.2445988e-05 | AK14: [CHF/kg]
L15: Parameter | M15: Country | N15: Value | O15: Unit | AE15: Denied maternity leave | AF15: =$N$29*W$33*VLOOKUP($AE$15,'Monetization factors'!$C$6:$I$28, 7,FALSE) -> 0.0001162673 | AG15: =$N$29*X$33*VLOOKUP($AE$15,'Monetization factors'!$C$6:$I$28, 7,FALSE) -> 0.00010677609 | AH15: =$N$29*Y$33*VLOOKUP($AE$15,'Monetization factors'!$C$6:$I$28, 7,FALSE) -> 0.00011796723 | AI15: =$O$29*Z$33*VLOOKUP($AE$15,'Monetization factors'!$C$6:$I$28, 7,FALSE) -> 3.6231037e-05 | AJ15: =$O$29*AA$33*VLOOKUP($AE$15,'Monetization factors'!$C$6:$I$28, 7,FALSE) -> 5.8841838e-05 | AK15: [CHF/kg]
L16: Annual hours worked in Agriculture | M16: Uruguay | N16: =D61*D51*(52-X14) -> 3.0889971e+08 | O16: h/year | AE16: Insured non-fatal incidents | AF16: =$N$30*W$34*VLOOKUP($AE$16,'Monetization factors'!$C$6:$I$28, 7,FALSE) -> 0.0024868883 | AG16: =$N$30*X$34*VLOOKUP($AE$16,'Monetization factors'!$C$6:$I$28, 7,FALSE) -> 0.002283877 | AH16: =$N$30*Y$34*VLOOKUP($AE$16,'Monetization factors'!$C$6:$I$28, 7,FALSE) -> 0.0025232487 | AI16: =$O$30*Z$34*VLOOKUP($AE$16,'Monetization factors'!$C$6:$I$28, 7,FALSE) -> 0.0002557744 | AJ16: =$O$30*AA$34*VLOOKUP($AE$16,'Monetization factors'!$C$6:$I$28, 7,FALSE) -> 0.00041539623 | AK16: [CHF/kg]
M17: Switzerland | N17: =D59*D50*(52-X13) -> 225212160 | O17: h/year | V17: Workload estimation by production system | AE17: Uninsured non-fatal incidents | AF17: =$N$31*W$34*VLOOKUP($AE$17,'Monetization factors'!$C$6:$I$28, 7,FALSE) -> 0.00020870513 | AG17: =$N$31*X$34*VLOOKUP($AE$17,'Monetization factors'!$C$6:$I$28, 7,FALSE) -> 0.00019166798 | AH17: =$N$31*Y$34*VLOOKUP($AE$17,'Monetization factors'!$C$6:$I$28, 7,FALSE) -> 0.00021175658 | AI17: =$O$31*Z$34*VLOOKUP($AE$17,'Monetization factors'!$C$6:$I$28, 7,FALSE) -> 0.00011345865 | AJ17: =$O$31*AA$34*VLOOKUP($AE$17,'Monetization factors'!$C$6:$I$28, 7,FALSE) -> 0.0001842651 | AK17: [CHF/kg]
C18: 9–14 | D18: 5450 | E18: indiv. | F18: 2024 | V18: (Appendix C.4) | AE18: Fatal incidents | AF18: =$N$32*W$34*VLOOKUP($AE$18,'Monetization factors'!$C$6:$I$28, 7,FALSE) -> 0.00398611 | AG18: =$N$32*X$34*VLOOKUP($AE$18,'Monetization factors'!$C$6:$I$28, 7,FALSE) -> 0.0036607133 | AH18: =$N$32*Y$34*VLOOKUP($AE$18,'Monetization factors'!$C$6:$I$28, 7,FALSE) -> 0.0040443904 | AI18: =$O$32*Z$34*VLOOKUP($AE$18,'Monetization factors'!$C$6:$I$28, 7,FALSE) -> 0.0018153192 | AJ18: =$O$32*AA$34*VLOOKUP($AE$18,'Monetization factors'!$C$6:$I$28, 7,FALSE) -> 0.0029482104 | AK18: [CHF/kg]
B19: Proportion of employed children engaged in agriculture | C19: 5–14 | D19: 28.4 | E19: % | F19: 2016 | G19: ILAB | H19: Prevalence and sectoral distribution of child labour | I19: Agricultural | V19: Table 10 (Appendix C.4) : Workload per production system estimations (Ti) | AE19: Total | AF19: =SUM(AF8:AF18) -> 0.71809779 | AG19: =SUM(AG8:AG18) -> 0.65947757 | AH19: =SUM(AH8:AH18) -> 0.728597 | AI19: =SUM(AI8:AI18) -> 0.060358252 | AJ19: =SUM(AJ8:AJ18) -> 0.09802619 | AK19: [CHF/kg]
B20: School attendance | C20: 7–12 | D20: 99.8 | E20: % | F20: 2024 | G20: CEPALSTAT | H20: School attendance, by age group, quintiles, and area (2024) | I20: National | V20: Country | W20: Production system i | X20: [h / animal / yr] | Y20: Tᵢ [h/kg]
C21: 13–19 | D21: 87.6 | E21: % | F21: 2024 | L21: Category | M21: Impact | N21: Value for Switzerland | O21: Value for Uruguay | P21: Unit | Q21: Description | V21: Switzerland | W21: Intensive | X21: =C161*AVERAGE($C$177:$C$178)+C163*C183*AVERAGE($C177,$C$178) -> 15.19 | Y21: =X21*('Production Systems Parameters'!D6+'Production Systems Parameters'!E6)/12/('Production Systems Parameters'!C6*'Production Systems Parameters'!C21/100) -> 0.094996873
B22: Weekly hours worked by children | C22: 7–14 | D22: 21.9 | E22: h/week | F22: 2009 | G22: Worl Bank (ILO, UNICEF) | H22: Average working hours of children, working only | I22: National | L22: Wage gaps | M22: Gender wage gap | N22: =ABS(D42-D46)*'Monetization factors'!D45 -> 1230.345 | O22: =ABS(D43-D47)*'Monetization factors'!D45 -> 146.11 | P22: CHF | Q22: Difference between males and females monthly earnings in agriculture | W22: Semi-intensive | X22: =D161*AVERAGE($C$177:$C$178)+(D163+D165)*$C$183*AVERAGE($C178,$C$178) -> 12.4 | Y22: =X22*('Production Systems Parameters'!D7+'Production Systems Parameters'!E7)/12/('Production Systems Parameters'!C7*'Production Systems Parameters'!C21/100) -> 0.087242026
B23: Sources : | M23: Wage gap with minimum wage | N23: =ABS(D42-D44)*D62/D59*'Monetization factors'!D45 -> 148.35099 | O23: =(IF(D43>D45,0,ABS(D45-D43)*D63/D61)+ IF(D47>D45,0,ABS(D47-D45)*(1-D63/D61)))*'Monetization factors'!D45 -> 0 | P23: CHF | Q23: Difference between the average monthly earnings of agricultural workers and the national statutory nominal gross monthly minimum wage, weighted by the proportion of female workers in the sector | W23: Extensive | X23: =E161*AVERAGE($C$177:$C$178)+(E163+E165)*$C$183*AVERAGE(C177,C178) -> 11.34 | Y23: =X23*('Production Systems Parameters'!D8+'Production Systems Parameters'!E8)/12/('Production Systems Parameters'!C8*'Production Systems Parameters'!C21/100) -> 0.096385809
B24: ENSANNA : Encuesta Nacional sobre las Actividades de Niñas, Niños y Adolescentes - 2024. Instituto Nacional de Estadística | L24: Child labour | M24: Children 5–14 in hazardous work | N24: 0 | O24: =SUM(D13:D18)*D19*D22*52/N16 -> 0.57061712 | P24: %* | Q24: Proportion of agricultural work performed by children aged 5–14 engaged in hazardous work | V24: Uruguay | W24: Semi-Intensive | X24: =C192/C191*'Production Systems Parameters'!D9/('Production Systems Parameters'!D9+'Production Systems Parameters'!E9)+D192/D191*'Production Systems Parameters'!E9/('Production Systems Parameters'!E9+'Production Systems Parameters'!D9) -> 5.002256 | Y24: =C192/C191*'Production Systems Parameters'!D9/12/('Production Systems Parameters'!C9*'Production Systems Parameters'!C21/100)+D192/D191*'Production Systems Parameters'!E9/12/('Production Systems Parameters'!C9*'Production Systems Parameters'!C21/100) -> 0.046306
B25: https://www.gub.uy/instituto-nacional-estadistica/comunicacion/publicaciones/encuesta-nacional-sobre-actividades-ninas-ninos-adolescentes-ensanna. | M25: Children 5–11 in non-hazardous work | N25: 0 | O25: =(N9-N11)*D19*D22*52/N16 -> 1.201437 | P25: %* | Q25: Proportion of agricultural work performed by children aged 5–11 engaged in non-hazardous work | W25: Extensive | X25: =E192/E191 -> 6.1263158 | Y25: =E192/E191*'Production Systems Parameters'!D10/12/('Production Systems Parameters'!C10*'Production Systems Parameters'!C21/100) -> 0.075204311
B26: ILAB : U.S. Department of Labor. Child Labor in Uruguay | M26: Children 12–14 in non-hazardous work | N26: 0 | O26: =(N10-N12)*D19*D22*52/N16 -> 0.85592567 | P26: %* | Q26: Proportion of agricultural work performed by children aged 12–14 engaged in non-hazardous work
B27: https://www.dol.gov/agencies/ilab/resources/reports/child-labor/uruguay | L27: Workers rights | M27: Absence of social security | N27: =D66 -> 7.5 | O27: =D67 -> 30 | P27: %* | Q27: Proportion of informal employment in the agricultural sector
B28: CEPALSTAT Economic Commission for Latin America and the Caribbean (ECLAC). CEPALSTAT Statistical Data Portal and Publications. 2026. | M28: Workers not on maternity leave | N28: =(D62/D59*D66/100*D48/D38*D36/52)*100 -> 0.020821232 | O28: =D63/D61*D67*D49/D39*D37/52 -> 0.075645462 | P28: %* | Q28: Proportion of agricultural workers with denied paid maternity leave | V28: Allocation factors derivation
B29: https://statistics.cepal.org/portal/cepalstat/ | M29: Denied maternity leaves | N29: =D36*D52*D40*N28/100*'Monetization factors'!D45 -> 2.8641528 | O29: =O28/100*'Monetization factors'!D45*D37*D53*D41 -> 1.6932405 | P29: CHF | Q29: Incomes not received due to the absence of maternity leave benefits in the agricultural sector | V29: (Appendix C.5)
B30: World Bank | L30: Occupational safety | M30: Insured non-fatal incidents | N30: =D54*(1-D66/100) -> 1589.15 | O30: =D55*(1-D67/100) -> 459.9 | P30: y⁻¹ | Q30: Annual number of non-fatal insured occupational incidents in the agricultural sector
B31: https://data.worldbank.org/indicator/SL.TLF.0714.WK.TM?most_recent_value_desc=false | M31: Uninsured non-fatal incidents | N31: =D54*D66/100 -> 128.85 | O31: =D55*D67/100 -> 197.1 | P31: y⁻¹ | Q31: Annual number of non-fatal uninsured occupational incidents in the agricultural sector | V31: Category | W31: Intensive - Switzerland | X31: Semi-Intensive - Switzerland | Y31: Extensive - Switzerland | Z31: Semi - Intensive - Uruguay | AA31: Extensive - Uruguay | AB31: Unit
M32: Fatal incidents | N32: =D56 -> 3 | O32: =D57*D60/D64 -> 3.844348 | P32: y⁻¹ | Q32: Annual number of fatal occupational incidents in the agricultural sector | V32: Wage gaps | W32: =Y21/($W$13/12) -> 0.00044690595 | X32: =Y22/($W$13/12) -> 0.00041042383 | Y32: =Y23/($W$13/12) -> 0.0004534401 | Z32: =Y24/($W$14/12) -> 0.00023556831 | AA32: =Y25/($W$14/12) -> 0.00038258007 | AB32: Month of work per kg of meat
L33: *annual percentages | V33: Workers rights & Child labour | W33: =Y21/$W$13 -> 3.7242162e-05 | X33: =Y22/$W$13 -> 3.4201986e-05 | Y33: =Y23/$W$13 -> 3.7786675e-05 | Z33: =Y24/$W$14 -> 1.9630693e-05 | AA33: =Y25/$W$14 -> 3.1881673e-05 | AB33: FTE / kg of meat
B34: Table 7 (Appendix C.1) : Input data used for the assessment of livelihood impacts related to wage gaps, workers rights and occupational safety. | V34: Occupational safety | W34: =Y21/$N$17 -> 4.2181059e-10 | X34: =Y22/$N$17 -> 3.8737707e-10 | Y34: =Y23/$N$17 -> 4.2797782e-10 | Z34: =Y24/$N$16 -> 1.4990626e-10 | AA34: =Y25/$N$16 -> 2.4345866e-10 | AB34: % of agricultural labour required to produce 1 kg of meat, weighted by production process duration
B35: Parameter | C35: Country | D35: Value | E35: Unit | F35: Year | G35: Database / Source | H35: Indicator | I35: Sector
B36: Maternity leave duration | C36: Switzerland | D36: 14 | E36: weeks | F36: 2000 | G36: ILO maternity leave convention | I36: -
C37: Uruguay | D37: 14 | E37: weeks | F37: 2000
B38: Working life duration | C38: Switzerland | D38: 42.8 | E38: year | F38: 2024 | G38: Eurostat | H38: Duration of working life | I38: National
C39: Uruguay | D39: =60-15 -> 45 | E39: year | F39: - | G39: Law N°16.713, art. 18 ; Law Nº 17.823, art. 162
B40: Hourly earnings of women in agriculture | C40: Switzerland | D40: 33.8 | E40: $/h | F40: 2024 | G40: ILOSTAT | H40: Average hourly earnings of employees | I40: Agricultural
C41: Uruguay | D41: 4.5 | E41: $/h | F41: 2024
B42: Monthly earnings of women in agriculture | C42: Switzerland | D42: 3658.4 | E42: $/month | F42: 2022 | G42: ILOSTAT | H42: Average monthly earnings of employees | I42: Agricultural
C43: Uruguay | D43: 608.2 | E43: $/month | F43: 2022
B44: Monthly statutory nominal gross min. wage | C44: Switzerland | D44: 4221 | E44: $/month | F44: 2022 | G44: ILOSTAT | H44: Statutory nominal gross monthly minimum wage | I44: National
C45: Uruguay | D45: 470.3 | E45: $/month | F45: 2022
B46: Monthly earnings of men in agriculture | C46: Switzerland | D46: 4953.5 | E46: $/month | F46: 2022 | G46: ILOSTAT | H46: Average monthly earnings of employees | I46: Agricultural
C47: Uruguay | D47: 762 | E47: $/month | F47: 2022
B48: Fertility rate | C48: Switzerland | D48: 1.59 | E48: child/woman | F48: 2024 | G48: World Population Review | H48: Total Fertility Rate | I48: National
C49: Uruguay | D49: 1.75 | E49: child/woman | F49: 2024
B50: Weekly hours worked per person in agriculture | C50: Switzerland | D50: 44.6 | E50: h/week | F50: 2022 | G50: ILOSTAT | H50: Mean weekly hours actually worked per employed person | I50: Agricultural
C51: Uruguay | D51: 43.5 | E51: h/week | F51: 2022
B52: Weekly hours worked by women in agriculture | C52: Switzerland | D52: 30.6 | E52: h/week | F52: 2024 | G52: ILOSTAT | H52: Mean weekly hours actually worked per employed person | I52: Agricultural
C53: Uruguay | D53: 37.4 | E53: h/week | F53: 2024
B54: Number of non fatal incidents in agriculture | C54: Switzerland | D54: 1718 | E54: year⁻¹ | F54: 2022 | G54: ILOSTAT | H54: Case of non fatal occupational injury | I54: Agricultural
C55: Uruguay | D55: 657 | E55: year⁻¹ | F55: 2013
B56: Number of fatal incidents | C56: Switzerland | D56: 3 | E56: year⁻¹ | F56: 2022 | G56: ILOSTAT | H56: Case of fatal occupational injury | I56: Agricultural
C57: Uruguay | D57: 46 | E57: year⁻¹ | F57: 2018 | I57: National
B58: Number of agricultural workers | C58: Switzerland | D58: 140600 | E58: - | F58: 2018 | G58: ILOSTAT | H58: Employment by sex and economic activity | I58: Agricultural
C59: Switzerland | D59: 105200 | E59: - | F59: 2022
C60: Uruguay | D60: 136700 | E60: - | F60: 2018
C61: Uruguay | D61: 144500 | E61: - | F61: 2022
B62: Number of women agricultural worker | C62: Switzerland | D62: =29.2*1000 -> 29200 | E62: - | F62: 2022 | G62: ILOSTAT | H62: Employment by sex and economic activity | I62: Agricultural
C63: Uruguay | D63: =34.8*1000 -> 34800 | E63: - | F63: 2022
B64: Number of person employed in the country | C64: Uruguay | D64: =1635.7*10^3 -> 1635700 | E64: - | F64: 2018 | G64: ILOSTAT | H64: Employment by sex and economic activity | I64: National
B66: Proportion of informal employment in agriculture | C66: Switzerland | D66: 7.5 | E66: % | F66: 2022 | G66: ILOSTAT | H66: Proportion of informal employment in total employment | I66: Agricultural
C67: Uruguay | D67: 30 | E67: % | F67: 2022
B68: Sources :
B69: ILO Maternity leave convention
B70: https://normlex.ilo.org/dyn/nrmlx_en/f?p=NORMLEXPUB:12100:0::NO::P12100_ILO_CODE:C183
B71: Eurostat
B72: https://ec.europa.eu/eurostat/databrowser/view/lfsi_dwl_a__custom_22774658/default/table
B73: Law N°16.713, art. 18
B74: https://www.impo.com.uy/bases/leyes/16713-1995
B75: Law Nº 17.823, art. 162
B76: https://www.gub.uy/ministerio-desarrollo-social/comunicacion/publicaciones/codigo-ninez-adolescencia-ley-17823
B77: ILOSTAT
B78: https://ilostat.ilo.org/data/?cat_mode=subject
B79: World Population Review
... B90: Table 9 (Appendix C.3) : Number of bovine in each Swiss canton
B91: Canton | C91: number bovine [head]
B92: Basel-Stadt | C92: 250
B93: Genève | C93: 3165
B94: Liechtenstein | C94: 6165
B95: Uri | C95: 10789
B96: Ticino | C96: 11012
B97: Glarus | C97: 11743
B98: Nidwalden | C98: 11799
B99: Appenzell Innerrhoden | C99: 14745
B100: Schaffhausen | C100: 16973
B101: Zug | C101: 18328
B102: Obwalden | C102: 18582
B103: Appenzell Ausserrhoden | C103: 22024
... B118: Bern | C118: 294735
B119: * Top 5 Swiss cantons with the highest number of bovines
B120: Source :
B121: Identitas AG, 2026. Platform animal statistics | animal statistics.
B122: Distribution by canton (2026)
B123: URL : https://tierstatistik.identitas.ch/fr/cattle-map-canton.html
B126: Table 9 (Appendix C.3) : Agricultural working conditions by canton
B127: Canton | C127: Max Working hours | D127: Vacations | E127: FTE
C128: [h/week] | D128: [week/year] | E128: [h/year]
B129: Bern | C129: =10*5.5 -> 55 | D129: 4 | E129: =C129*(52-D129) -> 2640
B130: Luzern | C130: 52 | D130: 4 | E130: =C130*(52-D130) -> 2496
...

Sheet Health
B2: Health :
B4: method from Crosnier et al. (2025)
B5: Crosnier, A., Baudry, G., Jeangros, L., Meier, E.S., Cisco, G., Spring, L., Barjolle, D., 2025.
B6: True cost accounting for food application: Environmental, social and health impacts of bread.
B7: doi:10.1016/j.jclepro.2025.146224.
B10: Input Data : | L10: Impact assessment : | V10: Impact monetization :
B12: Table 14 Appendix (D.1) : input data used for the assessment of health impacts
B13: Parameter | C13: Sex | D13: Value | E13: Unit | F13: Year | G13: Database / Source | H13: Indicator | L13: DALYs attributable to individual red meat consumption at level 𝑥 | V13: Dietary impact of meat consumption :
B14: Swiss population | C14: female | D14: 4520522.3 | E14: cap. | F14: 2023 | G14: GBD | H14: Population, all ages | L14: DALYs_{red meat} (x) | V14: =M252*VLOOKUP('Monetization factors'!C27,'Monetization factors'!$C$6:$I$28, 7,FALSE)*365.25/1000 -> 2.0992405 | W14: [CHF/kg]
C15: male | D15: 4471213.4 | E15: cap. | L15: intake x | M15: Male | N15: Female
B16: DALYs Colon and rectum cancer | C16: female | D16: 16839.373 | E16: DALYs·yr^-1 | F16: 2023 | G16: GBD | H16: Cause of death or injury, all ages | L16: =B54 -> 0 | M16: =$D$17/$D$15*C54+$D$19/$D$15*D54+$D$21/$D$15*E54+$D$23/$D$15*F54 -> 0 | N16: =$D$16/$D$14*C54+$D$18/$D$14*D54+$D$20/$D$14*E54+$D$22/$D$14*F54 -> 0
C17: male | D17: 22818.289 | E17: DALYs·yr^-1 | L17: =B55 -> 1.1948816 | M17: =$D$17/$D$15*C55+$D$19/$D$15*D55+$D$21/$D$15*E55+$D$23/$D$15*F55 -> 3.0815426e-05 | N17: =$D$16/$D$14*C55+$D$18/$D$14*D55+$D$20/$D$14*E55+$D$22/$D$14*F55 -> 2.1747778e-05
B18: DALYs Diabetes mellitus type 2 | C18: female | D18: 22375.207 | E18: DALYs·yr^-1 | F18: 2023 | G18: GBD | H18: Cause of death or injury, all ages | L18: =B56 -> 2.3897631 | M18: =$D$17/$D$15*C56+$D$19/$D$15*D56+$D$21/$D$15*E56+$D$23/$D$15*F56 -> 6.1262751e-05 | N18: =$D$16/$D$14*C56+$D$18/$D$14*D56+$D$20/$D$14*E56+$D$22/$D$14*F56 -> 4.3235403e-05
C19: male | D19: 30564.88 | E19: DALYs·yr^-1 | L19: =B57 -> 3.5846447 | M19: =$D$17/$D$15*C57+$D$19/$D$15*D57+$D$21/$D$15*E57+$D$23/$D$15*F57 -> 9.1386065e-05 | N19: =$D$16/$D$14*C57+$D$18/$D$14*D57+$D$20/$D$14*E57+$D$22/$D$14*F57 -> 6.4494035e-05
B20: DALYs Ischemic heart disease | C20: female | D20: 51487.095 | E20: DALYs·yr^-1 | F20: 2023 | G20: GBD | H20: Cause of death or injury, all ages | L20: =B58 -> 4.7795262 | M20: =$D$17/$D$15*C58+$D$19/$D$15*D58+$D$21/$D$15*E58+$D$23/$D$15*F58 -> 0.00012122946 | N20: =$D$16/$D$14*C58+$D$18/$D$14*D58+$D$20/$D$14*E58+$D$22/$D$14*F58 -> 8.5554835e-05
C21: male | D21: 87721.598 | E21: DALYs·yr^-1 | L21: =B59 -> 5.9744078 | M21: =$D$17/$D$15*C59+$D$19/$D$15*D59+$D$21/$D$15*E59+$D$23/$D$15*F59 -> 0.00015083702 | N21: =$D$16/$D$14*C59+$D$18/$D$14*D59+$D$20/$D$14*E59+$D$22/$D$14*F59 -> 0.00010644896
B22: DALYs Ischemic stroke | C22: female | D22: 23936.115 | E22: DALYs·yr^-1 | F22: 2023 | G22: GBD | H22: Cause of death or injury, all ages | L22: =B60 -> 7.1692893 | M22: =$D$17/$D$15*C60+$D$19/$D$15*D60+$D$21/$D$15*E60+$D$23/$D$15*F60 -> 0.00018025283 | N22: =$D$16/$D$14*C60+$D$18/$D$14*D60+$D$20/$D$14*E60+$D$22/$D$14*F60 -> 0.00012720757
C23: male | D23: 21532.227 | E23: DALYs·yr^-1 | L23: =B61 -> 8.3641709 | M23: =$D$17/$D$15*C61+$D$19/$D$15*D61+$D$21/$D$15*E61+$D$23/$D$15*F61 -> 0.00020952099 | N23: =$D$16/$D$14*C61+$D$18/$D$14*D61+$D$20/$D$14*E61+$D$22/$D$14*F61 -> 0.00014786183
B24: Daily red meat intake | C24: female | D24: 43.3 | E24: g·day^-1 | F24: 2020 | G24: GDD | H24: All ages | L24: =B62 -> 9.5590525 | M24: =$D$17/$D$15*C62+$D$19/$D$15*D62+$D$21/$D$15*E62+$D$23/$D$15*F62 -> 0.00023868559 | N24: =$D$16/$D$14*C62+$D$18/$D$14*D62+$D$20/$D$14*E62+$D$22/$D$14*F62 -> 0.0001684429
C25: male | D25: 52.5 | E25: g·day^-1 | L25: =B63 -> 10.753934 | M25: =$D$17/$D$15*C63+$D$19/$D$15*D63+$D$21/$D$15*E63+$D$23/$D$15*F63 -> 0.00026779071 | N25: =$D$16/$D$14*C63+$D$18/$D$14*D63+$D$20/$D$14*E63+$D$22/$D$14*F63 -> 0.00018898193
B26: Sources : | L26: =B64 -> 11.948816 | M26: =$D$17/$D$15*C64+$D$19/$D$15*D64+$D$21/$D$15*E64+$D$23/$D$15*F64 -> 0.00029688044 | N26: =$D$16/$D$14*C64+$D$18/$D$14*D64+$D$20/$D$14*E64+$D$22/$D$14*F64 -> 0.00020951008
B27: GDB : Collaborative Network. Global Burden of Disease (GDB) Results. Ed. by Global Burden of Disease Collaborative Network. 2023. | L27: =B65 -> 13.143697 | M27: =$D$17/$D$15*C65+$D$19/$D$15*D65+$D$21/$D$15*E65+$D$23/$D$15*F65 -> 0.00032599887 | N27: =$D$16/$D$14*C65+$D$18/$D$14*D65+$D$20/$D$14*E65+$D$22/$D$14*F65 -> 0.00023005852
B28: https://vizhub.healthdata.org/gbd-results/ | L28: =B66 -> 14.338579 | M28: =$D$17/$D$15*C66+$D$19/$D$15*D66+$D$21/$D$15*E66+$D$23/$D$15*F66 -> 0.0003551901 | N28: =$D$16/$D$14*C66+$D$18/$D$14*D66+$D$20/$D$14*E66+$D$22/$D$14*F66 -> 0.00025065841
B29: GDD : The Global Nutrition and Policy Consortium. Global Dietary Database. | L29: =B67 -> 15.53346 | M29: =$D$17/$D$15*C67+$D$19/$D$15*D67+$D$21/$D$15*E67+$D$23/$D$15*F67 -> 0.00038449821 | N29: =$D$16/$D$14*C67+$D$18/$D$14*D67+$D$20/$D$14*E67+$D$22/$D$14*F67 -> 0.0002713409
B30: https://globaldietarydatabase.org/complete-survey-metadata | L30: =B68 -> 16.728342 | M30: =$D$17/$D$15*C68+$D$19/$D$15*D68+$D$21/$D$15*E68+$D$23/$D$15*F68 -> 0.00041396729 | N30: =$D$16/$D$14*C68+$D$18/$D$14*D68+$D$20/$D$14*E68+$D$22/$D$14*F68 -> 0.00029213715
L31: =B69 -> 17.923223 | M31: =$D$17/$D$15*C69+$D$19/$D$15*D69+$D$21/$D$15*E69+$D$23/$D$15*F69 -> 0.00044364142 | N31: =$D$16/$D$14*C69+$D$18/$D$14*D69+$D$20/$D$14*E69+$D$22/$D$14*F69 -> 0.00031307833
L32: =B70 -> 19.118105 | M32: =$D$17/$D$15*C70+$D$19/$D$15*D70+$D$21/$D$15*E70+$D$23/$D$15*F70 -> 0.00047356471 | N32: =$D$16/$D$14*C70+$D$18/$D$14*D70+$D$20/$D$14*E70+$D$22/$D$14*F70 -> 0.00033419559
B33: Table 15 (Appendix D.1) : Average Daily Consumption of Red Meat and Related Meat Types | L33: =B71 -> 20.312986 | M33: =$D$17/$D$15*C71+$D$19/$D$15*D71+$D$21/$D$15*E71+$D$23/$D$15*F71 -> 0.00050378123 | N33: =$D$16/$D$14*C71+$D$18/$D$14*D71+$D$20/$D$14*E71+$D$22/$D$14*F71 -> 0.0003555201
B34: Food and Food Groups | C34: Intake [g/day] | L34: =B72 -> 21.507868 | M34: =$D$17/$D$15*C72+$D$19/$D$15*D72+$D$21/$D$15*E72+$D$23/$D$15*F72 -> 0.00053433508 | N34: =$D$16/$D$14*C72+$D$18/$D$14*D72+$D$20/$D$14*E72+$D$22/$D$14*F72 -> 0.00037708301
B35: Red meat, unprocessed | C35: 27.7 | L35: =B73 -> 22.70275 | M35: =$D$17/$D$15*C73+$D$19/$D$15*D73+$D$21/$D$15*E73+$D$23/$D$15*F73 -> 0.00056527035 | N35: =$D$16/$D$14*C73+$D$18/$D$14*D73+$D$20/$D$14*E73+$D$22/$D$14*F73 -> 0.00039891549
B36: Veal | C36: 2.7 | L36: =B74 -> 23.897631 | M36: =$D$17/$D$15*C74+$D$19/$D$15*D74+$D$21/$D$15*E74+$D$23/$D$15*F74 -> 0.00059663112 | N36: =$D$16/$D$14*C74+$D$18/$D$14*D74+$D$20/$D$14*E74+$D$22/$D$14*F74 -> 0.00042104868
B37: Rabbit | C37: 0.3 | L37: =B75 -> 25.092513 | M37: =$D$17/$D$15*C75+$D$19/$D$15*D75+$D$21/$D$15*E75+$D$23/$D$15*F75 -> 0.00062846148 | N37: =$D$16/$D$14*C75+$D$18/$D$14*D75+$D$20/$D$14*E75+$D$22/$D$14*F75 -> 0.00044351376
B38: Lamb | C38: 2.4 | L38: =B76 -> 26.287394 | M38: =$D$17/$D$15*C76+$D$19/$D$15*D76+$D$21/$D$15*E76+$D$23/$D$15*F76 -> 0.00066080553 | N38: =$D$16/$D$14*C76+$D$18/$D$14*D76+$D$20/$D$14*E76+$D$22/$D$14*F76 -> 0.00046634189
B39: Horse meat | C39: 1 | L39: =B77 -> 27.482276 | M39: =$D$17/$D$15*C77+$D$19/$D$15*D77+$D$21/$D$15*E77+$D$23/$D$15*F77 -> 0.00069370736 | N39: =$D$16/$D$14*C77+$D$18/$D$14*D77+$D$20/$D$14*E77+$D$22/$D$14*F77 -> 0.00048956421
B40: Beef | C40: 12.1 | L40: =B78 -> 28.677157 | M40: =$D$17/$D$15*C78+$D$19/$D$15*D78+$D$21/$D$15*E78+$D$23/$D$15*F78 -> 0.00072721104 | N40: =$D$16/$D$14*C78+$D$18/$D$14*D78+$D$20/$D$14*E78+$D$22/$D$14*F78 -> 0.0005132119
B41: Pork | C41: 9.2 | L41: =B79 -> 29.872039 | M41: =$D$17/$D$15*C79+$D$19/$D$15*D79+$D$21/$D$15*E79+$D$23/$D$15*F79 -> 0.00076136068 | N41: =$D$16/$D$14*C79+$D$18/$D$14*D79+$D$20/$D$14*E79+$D$22/$D$14*F79 -> 0.00053731611
B42: Sources : | L42: =B80 -> 31.06692 | M42: =$D$17/$D$15*C80+$D$19/$D$15*D80+$D$21/$D$15*E80+$D$23/$D$15*F80 -> 0.00079620035 | N42: =$D$16/$D$14*C80+$D$18/$D$14*D80+$D$20/$D$14*E80+$D$22/$D$14*F80 -> 0.000561908
B43: FSVO. Food consumption data from the First Swiss National Nutrition Survey menuCH 2014-15, | L43: =B81 -> 32.261802 | M43: =$D$17/$D$15*C81+$D$19/$D$15*D81+$D$21/$D$15*E81+$D$23/$D$15*F81 -> 0.00083177416 | N43: =$D$16/$D$14*C81+$D$18/$D$14*D81+$D$20/$D$14*E81+$D$22/$D$14*F81 -> 0.00058701873
B44: Version 3.0. Ed. by Federal Food Safety and Veterinary Office. | L44: =B82 -> 33.456684 | M44: =$D$17/$D$15*C82+$D$19/$D$15*D82+$D$21/$D$15*E82+$D$23/$D$15*F82 -> 0.00086812619 | N44: =$D$16/$D$14*C82+$D$18/$D$14*D82+$D$20/$D$14*E82+$D$22/$D$14*F82 -> 0.00061267946
B45: https://opendata.swiss/fr/dataset/menuch- portionsgrossen/resource/34a6986a- e880- 428d- beaa- e96db77001f4 | L45: =B83 -> 34.651565 | M45: =$D$17/$D$15*C83+$D$19/$D$15*D83+$D$21/$D$15*E83+$D$23/$D$15*F83 -> 0.00090977947 | N45: =$D$16/$D$14*C83+$D$18/$D$14*D83+$D$20/$D$14*E83+$D$22/$D$14*F83 -> 0.00064209056
L46: =B84 -> 35.846447 | M46: =$D$17/$D$15*C84+$D$19/$D$15*D84+$D$21/$D$15*E84+$D$23/$D$15*F84 -> 0.00095393167 | N46: =$D$16/$D$14*C84+$D$18/$D$14*D84+$D$20/$D$14*E84+$D$22/$D$14*F84 -> 0.00067324332
L47: =B85 -> 37.041328 | M47: =$D$17/$D$15*C85+$D$19/$D$15*D85+$D$21/$D$15*E85+$D$23/$D$15*F85 -> 0.00099917005 | N47: =$D$16/$D$14*C85+$D$18/$D$14*D85+$D$20/$D$14*E85+$D$22/$D$14*F85 -> 0.00070513216
L48: =B86 -> 38.23621 | M48: =$D$17/$D$15*C86+$D$19/$D$15*D86+$D$21/$D$15*E86+$D$23/$D$15*F86 -> 0.0010457621 | N48: =$D$16/$D$14*C86+$D$18/$D$14*D86+$D$20/$D$14*E86+$D$22/$D$14*F86 -> 0.00073794508
L49: =B87 -> 39.431091 | M49: =$D$17/$D$15*C87+$D$19/$D$15*D87+$D$21/$D$15*E87+$D$23/$D$15*F87 -> 0.0010935893 | N49: =$D$16/$D$14*C87+$D$18/$D$14*D87+$D$20/$D$14*E87+$D$22/$D$14*F87 -> 0.00077159549
B50: Table 16 (Appendix D.2): Derived Population Attributable Fractions (PAFs) for diseases associated | L50: =B88 -> 40.625973 | M50: =$D$17/$D$15*C88+$D$19/$D$15*D88+$D$21/$D$15*E88+$D$23/$D$15*F88 -> 0.0011425425 | N50: =$D$16/$D$14*C88+$D$18/$D$14*D88+$D$20/$D$14*E88+$D$22/$D$14*F88 -> 0.00080600356
B51: with suboptimal red meat consumption, by red meat intake levels. | L51: =B89 -> 41.820855 | M51: =$D$17/$D$15*C89+$D$19/$D$15*D89+$D$21/$D$15*E89+$D$23/$D$15*F89 -> 0.0011925247 | N51: =$D$16/$D$14*C89+$D$18/$D$14*D89+$D$20/$D$14*E89+$D$22/$D$14*F89 -> 0.00084109849
B52: Intake | C52: PAF | L52: =B90 -> 43.015736 | M52: =$D$17/$D$15*C90+$D$19/$D$15*D90+$D$21/$D$15*E90+$D$23/$D$15*F90 -> 0.0012434393 | N52: =$D$16/$D$14*C90+$D$18/$D$14*D90+$D$20/$D$14*E90+$D$22/$D$14*F90 -> 0.00087680979
B53: [g/day] | C53: Colon and Rectum Cancer | D53: Type 2 Diabetes | E53: Ischemic Heart Disease | F53: Ischemic Stroke | L53: =B91 -> 44.210618 | M53: =$D$17/$D$15*C91+$D$19/$D$15*D91+$D$21/$D$15*E91+$D$23/$D$15*F91 -> 0.0012951727 | N53: =$D$16/$D$14*C91+$D$18/$D$14*D91+$D$20/$D$14*E91+$D$22/$D$14*F91 -> 0.0009130546
B54: 0 | C54: 0 | D54: 0 | E54: 0 | F54: 0 | L54: =B92 -> 45.405499 | M54: =$D$17/$D$15*C92+$D$19/$D$15*D92+$D$21/$D$15*E92+$D$23/$D$15*F92 -> 0.0013476246 | N54: =$D$16/$D$14*C92+$D$18/$D$14*D92+$D$20/$D$14*E92+$D$22/$D$14*F92 -> 0.00094975993
B55: 1.1948816 | C55: 0.00082164377 | D55: 0.0011465774 | E55: 0.00075052425 | F55: 0.00084299932 | L55: =B93 -> 46.600381 | M55: =$D$17/$D$15*C93+$D$19/$D$15*D93+$D$21/$D$15*E93+$D$23/$D$15*F93 -> 0.0014007077 | N55: =$D$16/$D$14*C93+$D$18/$D$14*D93+$D$20/$D$14*E93+$D$22/$D$14*F93 -> 0.00098686236
B56: 2.3897631 | C56: 0.001633419 | D56: 0.0022790967 | E56: 0.0014922206 | F56: 0.0016759399 | L56: =B94 -> 47.795262 | M56: =$D$17/$D$15*C94+$D$19/$D$15*D94+$D$21/$D$15*E94+$D$23/$D$15*F94 -> 0.0014543367 | N56: =$D$16/$D$14*C94+$D$18/$D$14*D94+$D$20/$D$14*E94+$D$22/$D$14*F94 -> 0.0010242998
B57: 3.5846447 | C57: 0.0024365076 | D57: 0.0033992418 | E57: 0.0022261463 | F57: 0.0025000265 | L57: =B95 -> 48.990144 | M57: =$D$17/$D$15*C95+$D$19/$D$15*D95+$D$21/$D$15*E95+$D$23/$D$15*F95 -> 0.0015084136 | N57: =$D$16/$D$14*C95+$D$18/$D$14*D95+$D$20/$D$14*E95+$D$22/$D$14*F95 -> 0.0010620014
B58: 4.7795262 | C58: 0.0032320916 | D58: 0.0045086963 | E58: 0.0029533589 | F58: 0.0033164639 | L58: =B96 -> 50.185025 | M58: =$D$17/$D$15*C96+$D$19/$D$15*D96+$D$21/$D$15*E96+$D$23/$D$15*F96 -> 0.0015628555 | N58: =$D$16/$D$14*C96+$D$18/$D$14*D96+$D$20/$D$14*E96+$D$22/$D$14*F96 -> 0.0010999074
B59: 5.9744078 | C59: 0.0040213531 | D59: 0.0056091441 | E59: 0.0036749156 | F59: 0.0041264569 | L59: =B97 -> 51.379907 | M59: =$D$17/$D$15*C97+$D$19/$D$15*D97+$D$21/$D$15*E97+$D$23/$D$15*F97 -> 0.0016175911 | N59: =$D$16/$D$14*C97+$D$18/$D$14*D97+$D$20/$D$14*E97+$D$22/$D$14*F97 -> 0.0011379664
B60: 7.1692893 | C60: 0.0048054741 | D60: 0.0067022691 | E60: 0.0043918738 | F60: 0.0049312103 | L60: =B98 -> 52.574789 | M60: =$D$17/$D$15*C98+$D$19/$D$15*D98+$D$21/$D$15*E98+$D$23/$D$15*F98 -> 0.0016725513 | N60: =$D$16/$D$14*C98+$D$18/$D$14*D98+$D$20/$D$14*E98+$D$22/$D$14*F98 -> 0.0011761287
B61: 8.3641709 | C61: 0.0055856365 | D61: 0.007789755 | E61: 0.0051052909 | F61: 0.0057319289 | L61: =B99 -> 53.76967 | M61: =$D$17/$D$15*C99+$D$19/$D$15*D99+$D$21/$D$15*E99+$D$23/$D$15*F99 -> 0.0017276597 | N61: =$D$16/$D$14*C99+$D$18/$D$14*D99+$D$20/$D$14*E99+$D$22/$D$14*F99 -> 0.0012143398
B62: 9.5590525 | C62: 0.0063630224 | D62: 0.0088732856 | E62: 0.0058162243 | F62: 0.0065298174 | L62: =B100 -> 54.964552 | M62: =$D$17/$D$15*C100+$D$19/$D$15*D100+$D$21/$D$15*E100+$D$23/$D$15*F100 -> 0.0017828528 | N62: =$D$16/$D$14*C100+$D$18/$D$14*D100+$D$20/$D$14*E100+$D$22/$D$14*F100 -> 0.0012525547
B63: 10.753934 | C63: 0.0071388138 | D63: 0.0099545448 | E63: 0.0065257313 | F63: 0.0073260807 | L63: =B101 -> 56.159433 | M63: =$D$17/$D$15*C101+$D$19/$D$15*D101+$D$21/$D$15*E101+$D$23/$D$15*F101 -> 0.0018380771 | N63: =$D$16/$D$14*C101+$D$18/$D$14*D101+$D$20/$D$14*E101+$D$22/$D$14*F101 -> 0.0012907356
B64: 11.948816 | C64: 0.0079141926 | D64: 0.011035216 | E64: 0.0072348693 | F64: 0.0081219236 | L64: =B102 -> 57.354315 | M64: =$D$17/$D$15*C102+$D$19/$D$15*D102+$D$21/$D$15*E102+$D$23/$D$15*F102 -> 0.0018932816 | N64: =$D$16/$D$14*C102+$D$18/$D$14*D102+$D$20/$D$14*E102+$D$22/$D$14*F102 -> 0.0013288467
B65: 13.143697 | C65: 0.0086903409 | D65: 0.012116984 | E65: 0.0079446957 | F65: 0.0089185507 | L65: =B103 -> 58.549196 | M65: =$D$17/$D$15*C103+$D$19/$D$15*D103+$D$21/$D$15*E103+$D$23/$D$15*F103 -> 0.0019484097 | N65: =$D$16/$D$14*C103+$D$18/$D$14*D103+$D$20/$D$14*E103+$D$22/$D$14*F103 -> 0.0013668484
... B215: 192.37593 | C215: 0.17831947 | D215: 0.15763194 | E215: 0.1675934 | F215: 0.11887837 | L215: =B253 -> 237.78143 | M215: =$D$17/$D$15*C253+$D$19/$D$15*D253+$D$21/$D$15*E253+$D$23/$D$15*F253 -> 0.0067409595 | N215: =$D$16/$D$14*C253+$D$18/$D$14*D253+$D$20/$D$14*E253+$D$22/$D$14*F253 -> 0.0045795292
B216: 193.57081 | C216: 0.17908657 | D216: 0.15810213 | E216: 0.16834709 | F216: 0.11929839
B217: 194.76569 | C217: 0.17985223 | D217: 0.15857139 | E217: 0.16909989 | F217: 0.11971825
B218: 195.96058 | C218: 0.18061654 | D218: 0.1590398 | E218: 0.16985181 | F218: 0.12013793
B219: 197.15546 | C219: 0.1813796 | D219: 0.15950746 | E219: 0.17060289 | F219: 0.12055742 | L219: Curve fitting :
B220: 198.35034 | C220: 0.18214149 | D220: 0.15997443 | E220: 0.17135314 | F220: 0.12097672
B221: 199.54522 | C221: 0.18290225 | D221: 0.16044076 | E221: 0.17210256 | F221: 0.12139582
B222: 200.7401 | C222: 0.18366197 | D222: 0.16090648 | E222: 0.17285118 | F222: 0.1218147
B223: 201.93498 | C223: 0.18442069 | D223: 0.16137168 | E223: 0.173599 | F223: 0.12223337
B224: 203.12986 | C224: 0.18517845 | D224: 0.16183639 | E224: 0.17434605 | F224: 0.12265181
B225: 204.32475 | C225: 0.1859353 | D225: 0.16230063 | E225: 0.17509233 | F225: 0.12307002
B226: 205.51963 | C226: 0.18669128 | D226: 0.16276444 | E226: 0.17583785 | F226: 0.12348799
B227: 206.71451 | C227: 0.18744646 | D227: 0.16322788 | E227: 0.17658263 | F227: 0.12390573
B228: 207.90939 | C228: 0.18820084 | D228: 0.16369099 | E228: 0.17732665 | F228: 0.12432321
B229: 209.10427 | C229: 0.18895445 | D229: 0.16415379 | E229: 0.17806995 | F229: 0.12474044
B230: 210.29915 | C230: 0.1897073 | D230: 0.16461626 | E230: 0.17881251 | F230: 0.12515742
B231: 211.49404 | C231: 0.1904594 | D231: 0.16507844 | E231: 0.17955435 | F231: 0.12557414
... B237: 218.66332 | C237: 0.19495735 | D237: 0.16784579 | E237: 0.18399027 | F237: 0.12806889
B238: 219.85821 | C238: 0.19570466 | D238: 0.16830615 | E238: 0.18472709 | F238: 0.12848374 | L238: DALYs_{red meat}' (x)
B239: 221.05309 | C239: 0.1964513 | D239: 0.16876627 | E239: 0.18546319 | F239: 0.12889831 | L239: female | M239: =-3*10^(-14)*5 -> -1.5e-13 | N239: x^4 + | O239: =2*10^(-11)*4 -> 8e-11 | P239: x^3 + | Q239: =-5*10^(-9)*3 -> -1.5e-08 | R239: x^2 + | S239: =5*10^(-7)*2 -> 1e-06 | T239: x + | U239: =7*10^(-6) -> 7e-06
B240: 222.24797 | C240: 0.19719725 | D240: 0.16922618 | E240: 0.18619857 | F240: 0.1293126 | L240: male | M240: =-3*10^(-14)*5 -> -1.5e-13 | N240: x^4 + | O240: =3*10^(-11)*4 -> 1.2e-10 | P240: x^3 + | Q240: =-7*10^(-9)*3 -> -2.1e-08 | R240: x^2 + | S240: =7*10^(-7)*2 -> 1.4e-06 | T240: x + | U240: =9*10^(-6) -> 9e-06
B241: 223.44285 | C241: 0.19794251 | D241: 0.16968589 | E241: 0.18693324 | F241: 0.12972662
B242: 224.63773 | C242: 0.19868708 | D242: 0.17014534 | E242: 0.18766719 | F242: 0.13014037
B243: 225.83261 | C243: 0.19943095 | D243: 0.17060456 | E243: 0.18840042 | F243: 0.13055383 | L243: Estimation of the daily bovine meat Swiss consumption :
B244: 227.0275 | C244: 0.20017413 | D244: 0.17106353 | E244: 0.18913293 | F244: 0.13096702
B245: 228.22238 | C245: 0.20091661 | D245: 0.17152226 | E245: 0.18986471 | F245: 0.13137994 | L245: Daily bovine meat intake | M245: female | N245: =D24*C40/C35 -> 18.91444 | O245: g·day^-1
B246: 229.41726 | C246: 0.20165838 | D246: 0.17198076 | E246: 0.19059577 | F246: 0.13179257 | M246: male | N246: =D25*C40/C35 -> 22.933213 | O246: g·day^-1
B247: 230.61214 | C247: 0.20239944 | D247: 0.17243899 | E247: 0.19132611 | F247: 0.13220493
B248: 231.80702 | C248: 0.20313978 | D248: 0.17289695 | E248: 0.19205571 | F248: 0.13261702
B249: 233.0019 | C249: 0.2038794 | D249: 0.17335466 | E249: 0.19278458 | F249: 0.13302882 | L249: Impact assessment :
B250: 234.19679 | C250: 0.20461829 | D250: 0.17381216 | E250: 0.19351272 | F250: 0.13344036 | L250: female | M250: =(M239*N245^4+O239*N245^3+Q239*N245^2+S239*N245+U239)*1000/365.25 -> 5.7687178e-05 | N250: [DALYs∕cap∕kg bovine meat]
B251: 235.39167 | C251: 0.20535645 | D251: 0.17426941 | E251: 0.19424012 | F251: 0.13385163 | L251: male | M251: =(M240*N246^4+O240*N246^3+Q240*N246^2+S240*N246+U240)*1000/365.25 -> 8.6154108e-05 | N251: [DALYs∕cap∕kg bovine meat]
B252: 236.58655 | C252: 0.20609384 | D252: 0.17472642 | E252: 0.19496676 | F252: 0.13426261 | L252: aggregate | M252: =M250*D14/SUM(D14:D15)+M251*D15/SUM(D14:D15) -> 7.1842589e-05 | N252: [DALYs∕cap∕kg bovine meat]
B253: 237.78143 | C253: 0.20683055 | D253: 0.17518322 | E253: 0.19569272 | F253: 0.13467333
B255: Computation performed by :
B256: Idriss Komi, Center for Primary Care and Public Health (Unisanté), University of Lausanne, Lausanne, Switzerland,
B257: idriss.komi@unisanté.ch, ORCID: 0009-0008-1662-8368

Sheet Animal welfare
B2: Animal Welfare :
B4: Animal Quality Adjust Life Years (AQALY)
B5: method from Espinosa et al. (2025)
B6: Espinosa, R., Browning, H., Treich, N., 2025. Animal quality-adjusted life year (AQALY).
B7: doi:10.2139/ssrn.5255360, URL: https://ssrn.com/abstract=5255360,
B10: Input Data : | I10: Impact Assessment : | Q10: Impact Allocation : | Y10: Impact Monetization : | AI10: Animal Welfare Hidden Costs in animal DALYs
AI11: See Appendix E.6
B12: Table 18 (Appendix E.2): Estimated impact of welfare impairments on AQALY score. Mixed logit estimates, merged sample | I12: Impacts in absolute temrs | AI12: Method by Scherer et al. (2018)
B13: (Experts + UK Representative) with equal weights. | J13: Intensive - Switzerland | K13: Semi-Intensive - Switzerland | L13: Extensive - Switzerland | M13: Semi-Itensive - Uruguay | N13: Extensive - Uruguay | O13: Unit | R13: Intensive - Switzerland | S13: Semi-Intensive - Switzerland | T13: Extensive - Switzerland | U13: Semi-Itensive - Uruguay | V13: Extensive - Uruguay | W13: Unit | Z13: Intensive - Switzerland | AA13: Semi-Intensive - Switzerland | AB13: Extensive - Switzerland | AC13: Semi-Itensive - Uruguay | AD13: Extensive - Uruguay | AE13: Unit | AI13: Laura Scherer et al. “Framework for integrating animal welfare into life cycle sustainability assessment”. In: The International Journal of Life Cycle Assessment 23 (2018), pp. 1476–1490.
B14: Domain | C14: Grade | D14: Estimated Impact (QALY/nB) | E14: Std. Error | I14: Nutrition | J14: =C44*'Production Systems Parameters'!$E$6/12+'Production Systems Parameters'!$D$6/12*'Animal welfare'!D44 -> -0.31986667 | K14: =C44*'Production Systems Parameters'!$E$7/12+'Production Systems Parameters'!$D$7/12*'Animal welfare'!D44 -> -0.211 | L14: =$C44*'Production Systems Parameters'!$E$8/12+'Production Systems Parameters'!$D$8/12*$D44 -> -0.19645833 | M14: =$C44*'Production Systems Parameters'!$E$9/12+'Production Systems Parameters'!$D$9/12*$D44 -> -0.23653333 | N14: =$C44*'Production Systems Parameters'!$E$10/12+'Production Systems Parameters'!$D$10/12*$D44 -> -0.26052083 | O14: [AQALY/animal] | Q14: Nutrition | R14: =J24/('Production Systems Parameters'!$C$6*'Production Systems Parameters'!$C$21/100) -> 0.00027835757 | S14: =K24/('Production Systems Parameters'!$C$7*'Production Systems Parameters'!$C$21/100) -> 0.00023227408 | T14: =L24/('Production Systems Parameters'!$C$8*'Production Systems Parameters'!$C$21/100) -> 0.00028409091 | U14: =M24/('Production Systems Parameters'!$C$9*'Production Systems Parameters'!$C$21/100) -> 0.00011585366 | V14: =N24/('Production Systems Parameters'!$C$10*'Production Systems Parameters'!$C$21/100) -> 0 | W14: [AQALY/kg meat] | Y14: Nutrition | Z14: =R14*VLOOKUP('Monetization factors'!C$28,'Monetization factors'!C$6:J$28,7,FALSE)*$C$58*$C$60/$C$59^$C$60 -> 0.89660963 | AA14: =S14*VLOOKUP('Monetization factors'!C$28,'Monetization factors'!C$6:J$28,7,FALSE)*$C$58*$C$60/$C$59^$C$60 -> 0.74817142 | AB14: =T14*VLOOKUP('Monetization factors'!C$28,'Monetization factors'!C$6:J$28,7,FALSE)*$C$58*$C$60/$C$59^$C$60 -> 0.91507714 | AC14: =U14*VLOOKUP('Monetization factors'!C$28,'Monetization factors'!C$6:J$28,7,FALSE)*$C$58*$C$60/$C$59^$C$60 -> 0.37317292 | AD14: =V14*VLOOKUP('Monetization factors'!C$28,'Monetization factors'!C$6:J$28,7,FALSE)*$C$58*$C$60/$C$59^$C$60 -> 0 | AE14: [CHF/kg] | AI14: doi: 10.1007/s11367-017-1420-x.
B15: Nutrition | C15: Mild positive | D15: -0.1025 | E15: 0.024 | I15: Environment | J15: =C46*'Production Systems Parameters'!$E$6/12+'Production Systems Parameters'!$D$6/12*'Animal welfare'!D46 -> -0.72093333 | K15: =C46*'Production Systems Parameters'!$E$7/12+'Production Systems Parameters'!$D$7/12*'Animal welfare'!D46 -> -0.40155 | L15: =$C46*'Production Systems Parameters'!$E$8/12+'Production Systems Parameters'!$D$8/12*$D46 -> -0.31184167 | M15: =$C46*'Production Systems Parameters'!$E$9/12+'Production Systems Parameters'!$D$9/12*$D46 -> -0.42209167 | N15: =$C46*'Production Systems Parameters'!$E$10/12+'Production Systems Parameters'!$D$10/12*$D46 -> -0.41352917 | O15: [AQALY/animal] | Q15: Environment | R15: =J25/('Production Systems Parameters'!$C$6*'Production Systems Parameters'!$C$21/100) -> 0.0014418582 | S15: =K25/('Production Systems Parameters'!$C$7*'Production Systems Parameters'!$C$21/100) -> 5.6187461e-05 | T15: =L25/('Production Systems Parameters'!$C$8*'Production Systems Parameters'!$C$21/100) -> 0.00045094235 | U15: =M25/('Production Systems Parameters'!$C$9*'Production Systems Parameters'!$C$21/100) -> 4.1354745e-05 | V15: =N25/('Production Systems Parameters'!$C$10*'Production Systems Parameters'!$C$21/100) -> 0 | W15: [AQALY/kg meat] | Y15: Environment | Z15: =R15*VLOOKUP('Monetization factors'!C$28,'Monetization factors'!C$6:J$28,7,FALSE)*$C$58*$C$60/$C$59^$C$60 -> 4.6443284 | AA15: =S15*VLOOKUP('Monetization factors'!C$28,'Monetization factors'!C$6:J$28,7,FALSE)*$C$58*$C$60/$C$59^$C$60 -> 0.18098383 | AB15: =T15*VLOOKUP('Monetization factors'!C$28,'Monetization factors'!C$6:J$28,7,FALSE)*$C$58*$C$60/$C$59^$C$60 -> 1.4525176 | AC15: =U15*VLOOKUP('Monetization factors'!C$28,'Monetization factors'!C$6:J$28,7,FALSE)*$C$58*$C$60/$C$59^$C$60 -> 0.13320659 | AD15: =V15*VLOOKUP('Monetization factors'!C$28,'Monetization factors'!C$6:J$28,7,FALSE)*$C$58*$C$60/$C$59^$C$60 -> 0 | AE15: [CHF/kg]
C16: Neutral | D16: -0.1502 | E16: 0.0256 | I16: Health | J16: =C48*'Production Systems Parameters'!$E$6/12+'Production Systems Parameters'!$D$6/12*'Animal welfare'!D48 -> -0.3968 | K16: =C48*'Production Systems Parameters'!$E$7/12+'Production Systems Parameters'!$D$7/12*'Animal welfare'!D48 -> -0.19376667 | L16: =$C48*'Production Systems Parameters'!$E$8/12+'Production Systems Parameters'!$D$8/12*$D48 -> -0.12343333 | M16: =$C48*'Production Systems Parameters'!$E$9/12+'Production Systems Parameters'!$D$9/12*$D48 -> -0.19145 | N16: =$C48*'Production Systems Parameters'!$E$10/12+'Production Systems Parameters'!$D$10/12*$D48 -> -0.16368333 | O16: [AQALY/animal] | Q16: Health | R16: =J26/('Production Systems Parameters'!$C$6*'Production Systems Parameters'!$C$21/100) -> 0.0010934178 | S16: =K26/('Production Systems Parameters'!$C$7*'Production Systems Parameters'!$C$21/100) -> 0.00014110381 | T16: =L26/('Production Systems Parameters'!$C$8*'Production Systems Parameters'!$C$21/100) -> 0.00017849224 | U16: =M26/('Production Systems Parameters'!$C$9*'Production Systems Parameters'!$C$21/100) -> 0.00013410609 | V16: =N26/('Production Systems Parameters'!$C$10*'Production Systems Parameters'!$C$21/100) -> 0 | W16: [AQALY/kg meat] | Y16: Health | Z16: =R16*VLOOKUP('Monetization factors'!C$28,'Monetization factors'!C$6:J$28,7,FALSE)*$C$58*$C$60/$C$59^$C$60 -> 3.5219768 | AA16: =S16*VLOOKUP('Monetization factors'!C$28,'Monetization factors'!C$6:J$28,7,FALSE)*$C$58*$C$60/$C$59^$C$60 -> 0.45450548 | AB16: =T16*VLOOKUP('Monetization factors'!C$28,'Monetization factors'!C$6:J$28,7,FALSE)*$C$58*$C$60/$C$59^$C$60 -> 0.57493627 | AC16: =U16*VLOOKUP('Monetization factors'!C$28,'Monetization factors'!C$6:J$28,7,FALSE)*$C$58*$C$60/$C$59^$C$60 -> 0.43196532 | AD16: =V16*VLOOKUP('Monetization factors'!C$28,'Monetization factors'!C$6:J$28,7,FALSE)*$C$58*$C$60/$C$59^$C$60 -> 0 | AE16: [CHF/kg] | AI16: Input Data:
C17: Mild Negative | D17: -0.2399 | E17: 0.0219 | I17: Behavior | J17: =C50*'Production Systems Parameters'!$E$6/12+'Production Systems Parameters'!$D$6/12*'Animal welfare'!D50 -> -1.1741333 | K17: =C50*'Production Systems Parameters'!$E$7/12+'Production Systems Parameters'!$D$7/12*'Animal welfare'!D50 -> -0.49128333 | L17: =$C50*'Production Systems Parameters'!$E$8/12+'Production Systems Parameters'!$D$8/12*$D50 -> -0.22003333 | M17: =$C50*'Production Systems Parameters'!$E$9/12+'Production Systems Parameters'!$D$9/12*$D50 -> -0.44339167 | N17: =$C50*'Production Systems Parameters'!$E$10/12+'Production Systems Parameters'!$D$10/12*$D50 -> -0.29178333 | O17: [AQALY/animal] | Q17: Behavior | R17: =J27/('Production Systems Parameters'!$C$6*'Production Systems Parameters'!$C$21/100) -> 0.0041386023 | S17: =K27/('Production Systems Parameters'!$C$7*'Production Systems Parameters'!$C$21/100) -> 0.00093574109 | T17: =L27/('Production Systems Parameters'!$C$8*'Production Systems Parameters'!$C$21/100) -> 0.00031818182 | U17: =M27/('Production Systems Parameters'!$C$9*'Production Systems Parameters'!$C$21/100) -> 0.00073223054 | V17: =N27/('Production Systems Parameters'!$C$10*'Production Systems Parameters'!$C$21/100) -> 0 | W17: [AQALY/kg meat] | Y17: Behavior | Z17: =R17*VLOOKUP('Monetization factors'!C$28,'Monetization factors'!C$6:J$28,7,FALSE)*$C$58*$C$60/$C$59^$C$60 -> 13.330734 | AA17: =S17*VLOOKUP('Monetization factors'!C$28,'Monetization factors'!C$6:J$28,7,FALSE)*$C$58*$C$60/$C$59^$C$60 -> 3.014089 | AB17: =T17*VLOOKUP('Monetization factors'!C$28,'Monetization factors'!C$6:J$28,7,FALSE)*$C$58*$C$60/$C$59^$C$60 -> 1.0248864 | AC17: =U17*VLOOKUP('Monetization factors'!C$28,'Monetization factors'!C$6:J$28,7,FALSE)*$C$58*$C$60/$C$59^$C$60 -> 2.3585669 | AD17: =V17*VLOOKUP('Monetization factors'!C$28,'Monetization factors'!C$6:J$28,7,FALSE)*$C$58*$C$60/$C$59^$C$60 -> 0 | AE17: [CHF/kg] | AI17: Parameter | AJ17: Value | AK17: Unit
C18: Very Severe Negative | D18: -0.7148 | E18: 0.0393 | I18: Premature mortality | J18: - | K18: - | L18: - | M18: - | N18: - | O18: [AQALY/animal] | Q18: Premature mortality | R18: =J28/('Production Systems Parameters'!$C$6*'Production Systems Parameters'!$C$21/100) -> 0.0056676048 | S18: =K28/('Production Systems Parameters'!$C$7*'Production Systems Parameters'!$C$21/100) -> 0.0043089431 | T18: =L28/('Production Systems Parameters'!$C$8*'Production Systems Parameters'!$C$21/100) -> 0.00030820399 | U18: =M28/('Production Systems Parameters'!$C$9*'Production Systems Parameters'!$C$21/100) -> 0.0027868872 | V18: =N28/('Production Systems Parameters'!$C$10*'Production Systems Parameters'!$C$21/100) -> 0 | W18: [AQALY/kg meat] | Y18: Premature mortality | Z18: =R18*VLOOKUP('Monetization factors'!C$28,'Monetization factors'!C$6:J$28,7,FALSE)*$C$58*$C$60/$C$59^$C$60 -> 18.25576 | AA18: =S18*VLOOKUP('Monetization factors'!C$28,'Monetization factors'!C$6:J$28,7,FALSE)*$C$58*$C$60/$C$59^$C$60 -> 13.879414 | AB18: =T18*VLOOKUP('Monetization factors'!C$28,'Monetization factors'!C$6:J$28,7,FALSE)*$C$58*$C$60/$C$59^$C$60 -> 0.9927471 | AC18: =U18*VLOOKUP('Monetization factors'!C$28,'Monetization factors'!C$6:J$28,7,FALSE)*$C$58*$C$60/$C$59^$C$60 -> 8.9767631 | AD18: =V18*VLOOKUP('Monetization factors'!C$28,'Monetization factors'!C$6:J$28,7,FALSE)*$C$58*$C$60/$C$59^$C$60 -> 0 | AE18: [CHF/kg] | AI18: Life span( years) | AJ18: 20 | AK18: yr | AL18: MODIFMISENEGPAG
I19: Overall welfare score | J19: =('Production Systems Parameters'!$E$6/12+'Production Systems Parameters'!$D$6/12)*1 +SUM(J14:J17) -> -1.2784 | K19: =('Production Systems Parameters'!D7+'Production Systems Parameters'!E7)/12*1+SUM(K14:K17) -> 0.2024 | L19: =('Production Systems Parameters'!$E$8/12+'Production Systems Parameters'!$D$8/12)*1+SUM(L14:L17) -> 1.0649 | M19: =('Production Systems Parameters'!$E$9/12+'Production Systems Parameters'!$D$9/12)*1+SUM(M14:M17) -> 0.6232 | N19: =('Production Systems Parameters'!$E$10/12+'Production Systems Parameters'!$D$10/12)*1+SUM(N14:N17) -> 1.41215 | O19: [AQALY/animal] | Q19: Overall welfare score | R19: =J29/('Production Systems Parameters'!$C$6*'Production Systems Parameters'!$C$21/100) -> 0.012619841 | S19: =K29/('Production Systems Parameters'!$C$7*'Production Systems Parameters'!$C$21/100) -> 0.0056742495 | T19: =L29/('Production Systems Parameters'!$C$8*'Production Systems Parameters'!$C$21/100) -> 0.0015399113 | U19: =M29/('Production Systems Parameters'!$C$9*'Production Systems Parameters'!$C$21/100) -> 0.0038104323 | V19: =N29/('Production Systems Parameters'!$C$10*'Production Systems Parameters'!$C$21/100) -> 0 | W19: [AQALY/kg meat] | Y19: Overall welfare score | Z19: =R19*VLOOKUP('Monetization factors'!C$28,'Monetization factors'!C$6:J$28,7,FALSE)*$C$58*$C$60/$C$59^$C$60 -> 40.649409 | AA19: =S19*VLOOKUP('Monetization factors'!C$28,'Monetization factors'!C$6:J$28,7,FALSE)*$C$58*$C$60/$C$59^$C$60 -> 18.277164 | AB19: =T19*VLOOKUP('Monetization factors'!C$28,'Monetization factors'!C$6:J$28,7,FALSE)*$C$58*$C$60/$C$59^$C$60 -> 4.9601645 | AC19: =U19*VLOOKUP('Monetization factors'!C$28,'Monetization factors'!C$6:J$28,7,FALSE)*$C$58*$C$60/$C$59^$C$60 -> 12.273675 | AD19: =V19*VLOOKUP('Monetization factors'!C$28,'Monetization factors'!C$6:J$28,7,FALSE)*$C$58*$C$60/$C$59^$C$60 -> 0 | AE19: [CHF/kg] | AI19: Life expectancy (years) | AJ19: 5 | AK19: yr
B20: Environment | C20: Mild positive | D20: -0.1627 | E20: 0.0246 | I20: Max ideal welfare score | J20: =('Production Systems Parameters'!D6+'Production Systems Parameters'!E6)/12 -> 1.3333333 | K20: =('Production Systems Parameters'!D7+'Production Systems Parameters'!E7)/12 -> 1.5 | L20: ='Production Systems Parameters'!$E$8/12+'Production Systems Parameters'!$D$8/12 -> 1.9166667 | M20: ='Production Systems Parameters'!$E$9/12+'Production Systems Parameters'!$D$9/12 -> 1.9166667 | N20: ='Production Systems Parameters'!$E$10/12+'Production Systems Parameters'!$D$10/12 -> 2.5416667 | O20: [AQALY/animal] | AI20: Slaughter duration | AJ20: 1 | AK20: day
C21: Neutral | D21: -0.2179 | E21: 0.0262
C22: Mild Negative | D22: -0.3422 | E22: 0.021 | I22: Impact as a difference with the reference welfare state : | AI22: Impact assessment, allocation and monetization :
C23: Very Severe Negative | D23: -0.7392 | E23: 0.031 | J23: Intensive - Switzerland | K23: Semi-Intensive - Switzerland | L23: Extensive - Switzerland | M23: Semi-Itensive - Uruguay | N23: Extensive - Uruguay | O23: Unit
I24: Nutrition | J24: =ABS(J14-INDEX($J14:$N14,1,MATCH(MAX($J$19:$N$19),$J$19:$N$19,0))) -> 0.059345833 | K24: =ABS(K14-INDEX($J14:$N14,1,MATCH(MAX($J$19:$N$19),$J$19:$N$19,0))) -> 0.049520833 | L24: =ABS(L14-INDEX($J14:$N14,1,MATCH(MAX($J$19:$N$19),$J$19:$N$19,0))) -> 0.0640625 | M24: =ABS(M14-INDEX($J14:$N14,1,MATCH(MAX($J$19:$N$19),$J$19:$N$19,0))) -> 0.0239875 | N24: =ABS(N14-INDEX($J14:$N14,1,MATCH(MAX($J$19:$N$19),$J$19:$N$19,0))) -> 0 | O24: [AQALY/animal] | AI24: Production system | AJ24: Intensive - Switzerland | AK24: Semi-Intensive - Switzerland | AL24: Extensive - Switzerland | AM24: Semi-Intensive - Uruguay | AN24: Extensive - Uruguay
B25: Health | C25: Mild positive | D25: -0.0644 | E25: 0.0203 | I25: Environment | J25: =ABS(J15-INDEX($J15:$N15,1,MATCH(MAX($J$19:$N$19),$J$19:$N$19,0))) -> 0.30740417 | K25: =ABS(K15-INDEX($J15:$N15,1,MATCH(MAX($J$19:$N$19),$J$19:$N$19,0))) -> 0.011979167 | L25: =ABS(L15-INDEX($J15:$N15,1,MATCH(MAX($J$19:$N$19),$J$19:$N$19,0))) -> 0.1016875 | M25: =ABS(M15-INDEX($J15:$N15,1,MATCH(MAX($J$19:$N$19),$J$19:$N$19,0))) -> 0.0085625 | N25: =ABS(N15-INDEX($J15:$N15,1,MATCH(MAX($J$19:$N$19),$J$19:$N$19,0))) -> 0 | O25: [AQALY/animal] | AI25: I [%] | AJ25: ='Production Systems Parameters'!D6*100/('Production Systems Parameters'!D6+'Production Systems Parameters'!E6) -> 0 | AK25: ='Production Systems Parameters'!D7*100/('Production Systems Parameters'!D7+'Production Systems Parameters'!E7) -> 72.222222 | AL25: ='Production Systems Parameters'!D8*100/('Production Systems Parameters'!D8+'Production Systems Parameters'!E8) -> 100 | AM25: ='Production Systems Parameters'!D9*100/('Production Systems Parameters'!D9+'Production Systems Parameters'!E9) -> 84.782609 | AN25: ='Production Systems Parameters'!D10*100/('Production Systems Parameters'!D10+'Production Systems Parameters'!E10) -> 100
C26: Neutral | D26: -0.144 | E26: 0.0191 | I26: Health | J26: =ABS(J16-INDEX($J16:$N16,1,MATCH(MAX($J$19:$N$19),$J$19:$N$19,0))) -> 0.23311667 | K26: =ABS(K16-INDEX($J16:$N16,1,MATCH(MAX($J$19:$N$19),$J$19:$N$19,0))) -> 0.030083333 | L26: =ABS(L16-INDEX($J16:$N16,1,MATCH(MAX($J$19:$N$19),$J$19:$N$19,0))) -> 0.04025 | M26: =ABS(M16-INDEX($J16:$N16,1,MATCH(MAX($J$19:$N$19),$J$19:$N$19,0))) -> 0.027766667 | N26: =ABS(N16-INDEX($J16:$N16,1,MATCH(MAX($J$19:$N$19),$J$19:$N$19,0))) -> 0 | O26: [AQALY/animal] | AI26: Access to pasture prior to fattening ? | AJ26: no | AK26: yes | AL26: yes | AM26: yes | AN26: yes
C27: Mild Negative | D27: -0.2976 | E27: 0.0235 | I27: Behavior | J27: =ABS(J17-INDEX($J17:$N17,1,MATCH(MAX($J$19:$N$19),$J$19:$N$19,0))) -> 0.88235 | K27: =ABS(K17-INDEX($J17:$N17,1,MATCH(MAX($J$19:$N$19),$J$19:$N$19,0))) -> 0.1995 | L27: =ABS(L17-INDEX($J17:$N17,1,MATCH(MAX($J$19:$N$19),$J$19:$N$19,0))) -> 0.07175 | M27: =ABS(M17-INDEX($J17:$N17,1,MATCH(MAX($J$19:$N$19),$J$19:$N$19,0))) -> 0.15160833 | N27: =ABS(N17-INDEX($J17:$N17,1,MATCH(MAX($J$19:$N$19),$J$19:$N$19,0))) -> 0 | O27: [AQALY/animal] | AI27: Life Quality | AJ27: 0 | AK27: =(6.8136+1.9435*AK25-0.016979*AK25^2+0.000068633*AK25^3)/100 -> 0.84469245 | AL27: =(6.8136+1.9435*AL25-0.016979*AL25^2+0.000068633*AL25^3)/100 -> 1.000066 | AM27: =(6.8136+1.9435*AM25-0.016979*AM25^2+0.000068633*AM25^3)/100 -> 0.91368679 | AN27: =(6.8136+1.9435*AN25-0.016979*AN25^2+0.000068633*AN25^3)/100 -> 1.000066
C28: Very Severe Negative | D28: -0.8502 | E28: 0.0488 | I28: Premature mortality | J28: =J29-SUM(J24:J27) -> 1.2083333 | K28: =K29-SUM(K24:K27) -> 0.91866667 | L28: =L29-SUM(L24:L27) -> 0.0695 | M28: =M29-SUM(M24:M27) -> 0.577025 | N28: =N29-SUM(N24:N27) -> 0 | O28: [AQALY/animal]
I29: Overall welfare score | J29: =ABS(J19-INDEX($J19:$N19,1,MATCH(MAX($J$19:$N$19),$J$19:$N$19,0))) -> 2.69055 | K29: =ABS(K19-INDEX($J19:$N19,1,MATCH(MAX($J$19:$N$19),$J$19:$N$19,0))) -> 1.20975 | L29: =ABS(L19-INDEX($J19:$N19,1,MATCH(MAX($J$19:$N$19),$J$19:$N$19,0))) -> 0.34725 | M29: =ABS(M19-INDEX($J19:$N19,1,MATCH(MAX($J$19:$N$19),$J$19:$N$19,0))) -> 0.78895 | N29: =ABS(N19-INDEX($J19:$N19,1,MATCH(MAX($J$19:$N$19),$J$19:$N$19,0))) -> 0 | O29: [AQALY/animal] | AI29: Slaughter age [yr] | AJ29: ='Production Systems Parameters'!D6/12+'Production Systems Parameters'!E6/12 -> 1.3333333 | AK29: ='Production Systems Parameters'!D7/12+'Production Systems Parameters'!E7/12 -> 1.5 | AL29: ='Production Systems Parameters'!D8/12+'Production Systems Parameters'!E8/12 -> 1.9166667 | AM29: ='Production Systems Parameters'!D9/12+'Production Systems Parameters'!E9/12 -> 1.9166667 | AN29: ='Production Systems Parameters'!D10/12+'Production Systems Parameters'!E10/12 -> 2.5416667
B30: Behavior | C30: Mild positive | D30: -0.1148 | E30: 0.0264 | AI30: Life fraction | AJ30: =AJ29/$AJ$19 -> 0.26666667 | AK30: =AK29/$AJ$19 -> 0.3 | AL30: =AL29/$AJ$19 -> 0.38333333 | AM30: =AM29/$AJ$19 -> 0.38333333 | AN30: =AN29/$AJ$19 -> 0.50833333
C31: Neutral | D31: -0.2529 | E31: 0.0222 | AI31: Number affected [animal/kg meat] | AJ31: =1/('Production Systems Parameters'!C6*'Production Systems Parameters'!$C$21/100) -> 0.0046904315 | AK31: =1/('Production Systems Parameters'!C7*'Production Systems Parameters'!$C$21/100) -> 0.0046904315 | AL31: =1/('Production Systems Parameters'!C8*'Production Systems Parameters'!$C$21/100) -> 0.0044345898 | AM31: =1/('Production Systems Parameters'!C9*'Production Systems Parameters'!$C$21/100) -> 0.0048297513 | AN31: =1/('Production Systems Parameters'!C10*'Production Systems Parameters'!$C$21/100) -> 0.0048297513
C32: Mild Negative | D32: -0.3697 | E32: 0.0256 | AI32: Slaughter fraction | AJ32: =$AJ$20/(AJ29*365) -> 0.0020547945 | AK32: =$AJ$20/(AK29*365) -> 0.001826484 | AL32: =$AJ$20/(AL29*365) -> 0.0014294223 | AM32: =$AJ$20/(AM29*365) -> 0.0014294223 | AN32: =$AJ$20/(AN29*365) -> 0.001077925
C33: Very Severe Negative | D33: -0.8806 | E33: 0.0488
B34: Sources : | AI34: LL | AJ34: =AJ31*(1-AJ30) -> 0.0034396498 | AK34: =AK31*(1-AK30) -> 0.0032833021 | AL34: =AL31*(1-AL30) -> 0.0027346637 | AM34: =AM31*(1-AM30) -> 0.0029783466 | AN34: =AN31*(1-AN30) -> 0.0023746277
B35: Espinosa, R., Browning, H., Treich, N., 2025. Animal quality-adjusted life year (AQALY). | AI35: LD | AJ35: =AJ31*((AJ30-AJ32)*(1-AJ27)+AJ32) -> 0.0012507817 | AK35: =AK31*((AK30-AK32)*(1-AK27)+AK32) -> 0.00022577431 | AL35: =AL31*((AL30-AL32)*(1-AL27)+AL32) -> 6.2271247e-06 | AM35: =AM31*((AM30-AM32)*(1-AM27)+AM32) -> 0.00016610854 | AN35: =AN31*((AN30-AN32)*(1-AN27)+AN32) -> 5.0444151e-06
B36: doi:10.2139/ssrn.5255360, URL: https://ssrn.com/abstract=5255360, | I36: Animal welfare score per animal by indicator normalized over one year. | AI36: Animal welfare loss | AJ36: =AJ34+AJ35 -> 0.0046904315 | AK36: =AK34+AK35 -> 0.0035090764 | AL36: =AL34+AL35 -> 0.0027408908 | AM36: =AM34+AM35 -> 0.0031444552 | AN36: =AN34+AN35 -> 0.0023796721
J37: Intensive - Switzerland | K37: Semi-Intensive - Switzerland | L37: Extensive - Switzerland | M37: Semi-Itensive - Uruguay | N37: Extensive - Uruguay | O37: Unit
I38: Welfare impairments in Nutrition | J38: =J14/$J$20 -> -0.2399 | K38: =K14/$K$20 -> -0.14066667 | L38: =L14/$L$20 -> -0.1025 | M38: =M14/$M$20 -> -0.1234087 | N38: =N14/$N$20 -> -0.1025 | O38: [AQALY/animal] | AI38: Monetized AL | AJ38: =AJ36*($C$58^$C$60/$C$59^$C$60)*VLOOKUP('Monetization factors'!C$27,'Monetization factors'!C$6:J$28,7,FALSE) -> 12.086572 | AK38: =AK36*($C$58^$C$60/$C$59^$C$60)*VLOOKUP('Monetization factors'!C$27,'Monetization factors'!C$6:J$28,7,FALSE) -> 9.0423888 | AL38: =AL36*($C$58^$C$60/$C$59^$C$60)*VLOOKUP('Monetization factors'!C$27,'Monetization factors'!C$6:J$28,7,FALSE) -> 7.0628843 | AM38: =AM36*($C$58^$C$60/$C$59^$C$60)*VLOOKUP('Monetization factors'!C$27,'Monetization factors'!C$6:J$28,7,FALSE) -> 8.102812 | AN38: =AN36*($C$58^$C$60/$C$59^$C$60)*VLOOKUP('Monetization factors'!C$27,'Monetization factors'!C$6:J$28,7,FALSE) -> 6.1320753
I39: Welfare impairments in Environment | J39: =J15/$J$20 -> -0.5407 | K39: =K15/$K$20 -> -0.2677 | L39: =L15/$L$20 -> -0.1627 | M39: =M15/$M$20 -> -0.22022174 | N39: =N15/$N$20 -> -0.1627 | O39: [AQALY/animal] | AI39: Lives lost | AJ39: =AJ34*($C$58^$C$60/$C$59^$C$60)*VLOOKUP('Monetization factors'!C$27,'Monetization factors'!C$6:J$28,7,FALSE) -> 8.8634863 | AK39: =AK34*($C$58^$C$60/$C$59^$C$60)*VLOOKUP('Monetization factors'!C$27,'Monetization factors'!C$6:J$28,7,FALSE) -> 8.4606006 | AL39: =AL34*($C$58^$C$60/$C$59^$C$60)*VLOOKUP('Monetization factors'!C$27,'Monetization factors'!C$6:J$28,7,FALSE) -> 7.0468379 | AM39: =AM34*($C$58^$C$60/$C$59^$C$60)*VLOOKUP('Monetization factors'!C$27,'Monetization factors'!C$6:J$28,7,FALSE) -> 7.674774 | AN39: =AN34*($C$58^$C$60/$C$59^$C$60)*VLOOKUP('Monetization factors'!C$27,'Monetization factors'!C$6:J$28,7,FALSE) -> 6.1190765
B40: Table 17 (Appendix E.2) : Animal welfare assessment of French feedlot and pasture beef | I40: Welfare impairments in Health | J40: =J16/$J$20 -> -0.2976 | K40: =K16/$K$20 -> -0.12917778 | L40: =L16/$L$20 -> -0.0644 | M40: =M16/$M$20 -> -0.099886957 | N40: =N16/$N$20 -> -0.0644 | O40: [AQALY/animal] | AI40: Lives with disability | AJ40: =AJ35*($C$58^$C$60/$C$59^$C$60)*VLOOKUP('Monetization factors'!C$27,'Monetization factors'!C$6:J$28,7,FALSE) -> 3.2230859 | AK40: =AK35*($C$58^$C$60/$C$59^$C$60)*VLOOKUP('Monetization factors'!C$27,'Monetization factors'!C$6:J$28,7,FALSE) -> 0.58178816 | AL40: =AL35*($C$58^$C$60/$C$59^$C$60)*VLOOKUP('Monetization factors'!C$27,'Monetization factors'!C$6:J$28,7,FALSE) -> 0.016046411 | AM40: =AM35*($C$58^$C$60/$C$59^$C$60)*VLOOKUP('Monetization factors'!C$27,'Monetization factors'!C$6:J$28,7,FALSE) -> 0.428038 | AN40: =AN35*($C$58^$C$60/$C$59^$C$60)*VLOOKUP('Monetization factors'!C$27,'Monetization factors'!C$6:J$28,7,FALSE) -> 0.012998737
B41: and estimated impact on animal welfare score in each welfare domain | I41: Welfare impairments in Behavior | J41: =J17/$J$20 -> -0.8806 | K41: =K17/$K$20 -> -0.32752222 | L41: =L17/$L$20 -> -0.1148 | M41: =M17/$M$20 -> -0.23133478 | N41: =N17/$N$20 -> -0.1148 | O41: [AQALY/animal]
B42: Welfare level related to... | C42: Feedlot beef | D42: Pasture beef | I42: Premature mortality | J42: - | K42: - | L42: - | M42: - | N42: - | O42: [AQALY/animal]
B43: Nutrition | C43: Mild Negative | D43: Mild positive | I43: Actual welfare score | J43: =J19/$J$20 -> -0.9588 | K43: =K19/$K$20 -> 0.13493333 | L43: =L19/$L$20 -> 0.5556 | M43: =M19/$M$20 -> 0.32514783 | N43: =N19/$N$20 -> 0.5556 | O43: [AQALY/animal]
C44: =VLOOKUP(C43,C15:D18,2,FALSE) -> -0.2399 | D44: =VLOOKUP(D43,C15:D18,2,FALSE) -> -0.1025 | I44: Perfect Welfare State | J44: =J20/$J$20 -> 1 | K44: =K20/$K$20 -> 1 | L44: =L20/$L$20 -> 1 | M44: =M20/$M$20 -> 1 | N44: =N20/$N$20 -> 1 | O44: [AQALY/animal]
B45: Environment | C45: Severe Negative | D45: Mild positive | I45: Perfect welfare state represent the annual welfare score the animal would have under perfect welfare state, which is by definition set to 1.
C46: =AVERAGE(D22,D23) -> -0.5407 | D46: =VLOOKUP(D45,C20:D23,2,FALSE) -> -0.1627 | I46: Actual welfare state correspond to the annual welfare score the animal actualy exhibit in each production system
B47: Health | C47: Mild Negative | D47: Mild positive
C48: =VLOOKUP(C47,C25:D28,2,FALSE) -> -0.2976 | D48: =VLOOKUP(D47,C25:D28,2,FALSE) -> -0.0644
B49: Behavior | C49: Very Severe Negative | D49: Mild positive | I49: Figure 3 : Animal welfare score per animal by indicator normalized over one year.
C50: =VLOOKUP(C49,C30:D33,2,FALSE) -> -0.8806 | D50: =VLOOKUP(D49,C30:D33,2,FALSE) -> -0.1148
B51: Sources :
B52: Espinosa, R., Browning, H., Treich, N., 2025. Animal quality-adjusted life year (AQALY).
B53: doi:10.2139/ssrn.5255360, URL: https://ssrn.com/abstract=5255360,
B56: Table 20 (Appendix E.4) : Parameters used for the estimation of utility potential.
B57: Parameter | C57: Value | D57: Unit | E57: Source
B58: n_bovines | C58: =790 * 10^6 -> 790000000 | D58: number of cortical neurons | E58: Espinosa (2024)
B59: n_humans | C59: =24526 * 10^6 -> 24526000000 | D59: number of cortical neurons | E59: Espinosa (2024)
B60: ψ | C60: 1
B61: Source :
B62: Romain Espinosa. “Animals and social welfare”. In: Social Choice and Welfare 62.3 (2024), pp. 465–504. (Supplementary materials)
B63: doi: 10.1007/s00355-023-01495-x
